Workbook

Sheet Tổng hợp 
A1: Tên cuộc thi | B1: Lĩnh vực | C1: Đơn vị tổ chức | D1: Mô tả ngắn gọn | E1: Đối tượng tham gia | F1: Hình thức tham gia | G1: Cơ cấu vòng thi | H1: Cơ cấu giải thưởng | I1: Các mốc thời gian | J1: Mùa thi | K1: Deadline đăng ký | L1: Trạng thái | M1: Link nguồn chính thức
A2: ='Phân tích và chỉnh sửa'!B6 | B2: Khởi nghiệp | C2: ='Phân tích và chỉnh sửa'!B8 | D2: ='Phân tích và chỉnh sửa'!B9 | E2: ='Phân tích và chỉnh sửa'!B10 | F2: ='Phân tích và chỉnh sửa'!B11 | G2: ='Phân tích và chỉnh sửa'!B12 | H2: ='Phân tích và chỉnh sửa'!B13 | I2: ='Phân tích và chỉnh sửa'!B14 | J2: ='Phân tích và chỉnh sửa'!B15 | K2: ='Phân tích và chỉnh sửa'!B16 | L2: ='Phân tích và chỉnh sửa'!B17 | M2: ='Phân tích và chỉnh sửa'!B18
A3: ='Phân tích và chỉnh sửa'!B530 | B3: Khởi nghiệp | C3: ='Phân tích và chỉnh sửa'!B532 | D3: ='Phân tích và chỉnh sửa'!B533 | E3: ='Phân tích và chỉnh sửa'!B534 | F3: ='Phân tích và chỉnh sửa'!B535 | G3: ='Phân tích và chỉnh sửa'!B536 | H3: ='Phân tích và chỉnh sửa'!B537 | I3: ='Phân tích và chỉnh sửa'!B538 | J3: ='Phân tích và chỉnh sửa'!B539 | K3: ='Phân tích và chỉnh sửa'!B540 | L3: ='Phân tích và chỉnh sửa'!B541 | M3: ='Phân tích và chỉnh sửa'!B542
A4: ='Phân tích và chỉnh sửa'!B38 | B4: Khởi nghiệp | C4: ='Phân tích và chỉnh sửa'!B40 | D4: ='Phân tích và chỉnh sửa'!B41 | E4: ='Phân tích và chỉnh sửa'!B42 | F4: ='Phân tích và chỉnh sửa'!B43 | G4: ='Phân tích và chỉnh sửa'!B44 | H4: ='Phân tích và chỉnh sửa'!B45 | I4: ='Phân tích và chỉnh sửa'!B46 | J4: ='Phân tích và chỉnh sửa'!B47 | K4: ='Phân tích và chỉnh sửa'!B48 | L4: ='Phân tích và chỉnh sửa'!B49 | M4: ='Phân tích và chỉnh sửa'!B50
A5: ='Phân tích và chỉnh sửa'!B588 | B5: Khởi nghiệp | C5: ='Phân tích và chỉnh sửa'!B589 | D5: ='Phân tích và chỉnh sửa'!B577 | E5: ='Phân tích và chỉnh sửa'!B590 | F5: ='Phân tích và chỉnh sửa'!B591 | G5: ='Phân tích và chỉnh sửa'!B592 | H5: ='Phân tích và chỉnh sửa'!B593 | I5: ='Phân tích và chỉnh sửa'!B594 | J5: ='Phân tích và chỉnh sửa'!B595 | K5: ='Phân tích và chỉnh sửa'!B596 | L5: ='Phân tích và chỉnh sửa'!B597 | M5: ='Phân tích và chỉnh sửa'!B598
A6: ='Phân tích và chỉnh sửa'!B450 | B6: Khởi nghiệp | C6: ='Phân tích và chỉnh sửa'!B452 | D6: ='Phân tích và chỉnh sửa'!B453 | E6: ='Phân tích và chỉnh sửa'!B454 | F6: ='Phân tích và chỉnh sửa'!B455 | G6: ='Phân tích và chỉnh sửa'!B456 | H6: ='Phân tích và chỉnh sửa'!B457 | I6: ='Phân tích và chỉnh sửa'!B458 | J6: ='Phân tích và chỉnh sửa'!B459 | K6: ='Phân tích và chỉnh sửa'!B460 | L6: ='Phân tích và chỉnh sửa'!B461 | M6: ='Phân tích và chỉnh sửa'!B462
A7: ='Phân tích và chỉnh sửa'!B418 | B7: Khởi nghiệp | C7: ='Phân tích và chỉnh sửa'!B420 | D7: ='Phân tích và chỉnh sửa'!B421 | E7: ='Phân tích và chỉnh sửa'!B422 | F7: ='Phân tích và chỉnh sửa'!B423 | G7: ='Phân tích và chỉnh sửa'!B424 | H7: ='Phân tích và chỉnh sửa'!B425 | I7: ='Phân tích và chỉnh sửa'!B426 | J7: ='Phân tích và chỉnh sửa'!B427 | K7: ='Phân tích và chỉnh sửa'!B428 | L7: ='Phân tích và chỉnh sửa'!B429 | M7: ='Phân tích và chỉnh sửa'!B430
A8: ='Phân tích và chỉnh sửa'!B434 | B8: Khởi nghiệp | C8: ='Phân tích và chỉnh sửa'!B436 | D8: ='Phân tích và chỉnh sửa'!B437 | E8: ='Phân tích và chỉnh sửa'!B438 | F8: ='Phân tích và chỉnh sửa'!B439 | G8: ='Phân tích và chỉnh sửa'!B440 | H8: ='Phân tích và chỉnh sửa'!B441 | I8: ='Phân tích và chỉnh sửa'!B442 | J8: ='Phân tích và chỉnh sửa'!B443 | K8: ='Phân tích và chỉnh sửa'!B444 | L8: ='Phân tích và chỉnh sửa'!B445 | M8: ='Phân tích và chỉnh sửa'!B446
A9: ='Phân tích và chỉnh sửa'!B54 | B9: Khởi nghiệp | C9: ='Phân tích và chỉnh sửa'!B56 | D9: ='Phân tích và chỉnh sửa'!B57 | E9: ='Phân tích và chỉnh sửa'!B58 | F9: ='Phân tích và chỉnh sửa'!B59 | G9: ='Phân tích và chỉnh sửa'!B60 | H9: ='Phân tích và chỉnh sửa'!B61 | I9: ='Phân tích và chỉnh sửa'!B62 | J9: ='Phân tích và chỉnh sửa'!B63 | K9: ='Phân tích và chỉnh sửa'!B64 | L9: ='Phân tích và chỉnh sửa'!B65 | M9: ='Phân tích và chỉnh sửa'!B66
A10: ='Phân tích và chỉnh sửa'!B70 | B10: Khởi nghiệp | C10: ='Phân tích và chỉnh sửa'!B72 | D10: ='Phân tích và chỉnh sửa'!B73 | E10: ='Phân tích và chỉnh sửa'!B74 | F10: ='Phân tích và chỉnh sửa'!B75 | G10: ='Phân tích và chỉnh sửa'!B76 | H10: ='Phân tích và chỉnh sửa'!B77 | I10: ='Phân tích và chỉnh sửa'!B78 | J10: ='Phân tích và chỉnh sửa'!B79 | K10: ='Phân tích và chỉnh sửa'!B80 | L10: ='Phân tích và chỉnh sửa'!B81 | M10: ='Phân tích và chỉnh sửa'!B82
A11: ='Phân tích và chỉnh sửa'!B86 | B11: Khởi nghiệp | C11: ='Phân tích và chỉnh sửa'!B88 | D11: ='Phân tích và chỉnh sửa'!B89 | E11: ='Phân tích và chỉnh sửa'!B90 | F11: ='Phân tích và chỉnh sửa'!B91 | G11: ='Phân tích và chỉnh sửa'!B92 | H11: ='Phân tích và chỉnh sửa'!B93 | I11: ='Phân tích và chỉnh sửa'!B94 | J11: ='Phân tích và chỉnh sửa'!B95 | K11: ='Phân tích và chỉnh sửa'!B96 | L11: ='Phân tích và chỉnh sửa'!B97 | M11: ='Phân tích và chỉnh sửa'!B98
A12: ='Phân tích và chỉnh sửa'!B102 | B12: Khởi nghiệp | C12: ='Phân tích và chỉnh sửa'!B104 | D12: ='Phân tích và chỉnh sửa'!B105 | E12: ='Phân tích và chỉnh sửa'!B106 | F12: ='Phân tích và chỉnh sửa'!B107 | G12: ='Phân tích và chỉnh sửa'!B108 | H12: ='Phân tích và chỉnh sửa'!B109 | I12: ='Phân tích và chỉnh sửa'!B110 | J12: ='Phân tích và chỉnh sửa'!B111 | K12: ='Phân tích và chỉnh sửa'!B112 | L12: ='Phân tích và chỉnh sửa'!B113 | M12: ='Phân tích và chỉnh sửa'!B114
A13: ='Phân tích và chỉnh sửa'!B482 | B13: Khởi nghiệp | C13: ='Phân tích và chỉnh sửa'!B484 | D13: ='Phân tích và chỉnh sửa'!B485 | E13: ='Phân tích và chỉnh sửa'!B486 | F13: ='Phân tích và chỉnh sửa'!B487 | G13: ='Phân tích và chỉnh sửa'!B488 | H13: ='Phân tích và chỉnh sửa'!B489 | I13: ='Phân tích và chỉnh sửa'!B490 | J13: ='Phân tích và chỉnh sửa'!B491 | K13: ='Phân tích và chỉnh sửa'!B492 | L13: ='Phân tích và chỉnh sửa'!B493 | M13: ='Phân tích và chỉnh sửa'!B494
A14: ='Phân tích và chỉnh sửa'!B466 | B14: Khởi nghiệp | C14: ='Phân tích và chỉnh sửa'!B468 | D14: ='Phân tích và chỉnh sửa'!B469 | E14: ='Phân tích và chỉnh sửa'!B470 | F14: ='Phân tích và chỉnh sửa'!B471 | G14: ='Phân tích và chỉnh sửa'!B472 | H14: ='Phân tích và chỉnh sửa'!B473 | I14: ='Phân tích và chỉnh sửa'!B474 | J14: ='Phân tích và chỉnh sửa'!B475 | K14: ='Phân tích và chỉnh sửa'!B476 | L14: ='Phân tích và chỉnh sửa'!B477 | M14: ='Phân tích và chỉnh sửa'!B478
A15: ='Phân tích và chỉnh sửa'!B498 | B15: Khởi nghiệp | C15: ='Phân tích và chỉnh sửa'!B500 | D15: ='Phân tích và chỉnh sửa'!B501 | E15: ='Phân tích và chỉnh sửa'!B502 | F15: ='Phân tích và chỉnh sửa'!B503 | G15: ='Phân tích và chỉnh sửa'!B504 | H15: ='Phân tích và chỉnh sửa'!B505 | I15: ='Phân tích và chỉnh sửa'!B506 | J15: ='Phân tích và chỉnh sửa'!B507 | K15: ='Phân tích và chỉnh sửa'!B508 | L15: ='Phân tích và chỉnh sửa'!B509 | M15: ='Phân tích và chỉnh sửa'!B510
A16: ='Phân tích và chỉnh sửa'!B514 | B16: Khởi nghiệp | C16: ='Phân tích và chỉnh sửa'!B516 | D16: ='Phân tích và chỉnh sửa'!B517 | E16: ='Phân tích và chỉnh sửa'!B518 | F16: ='Phân tích và chỉnh sửa'!B519 | G16: ='Phân tích và chỉnh sửa'!B520 | H16: ='Phân tích và chỉnh sửa'!B521 | I16: ='Phân tích và chỉnh sửa'!B522 | J16: ='Phân tích và chỉnh sửa'!B523 | K16: ='Phân tích và chỉnh sửa'!B524 | L16: ='Phân tích và chỉnh sửa'!B525 | M16: ='Phân tích và chỉnh sửa'!B526
A17: ='Phân tích và chỉnh sửa'!B560 | B17: Khởi nghiệp | C17: ='Phân tích và chỉnh sửa'!B561 | D17: ='Phân tích và chỉnh sửa'!B549 | E17: ='Phân tích và chỉnh sửa'!B562 | F17: ='Phân tích và chỉnh sửa'!B563 | G17: ='Phân tích và chỉnh sửa'!B564 | H17: ='Phân tích và chỉnh sửa'!B565 | I17: ='Phân tích và chỉnh sửa'!B566 | J17: ='Phân tích và chỉnh sửa'!B567 | K17: ='Phân tích và chỉnh sửa'!B568 | L17: ='Phân tích và chỉnh sửa'!B569 | M17: ='Phân tích và chỉnh sửa'!B570
A18: ='Phân tích và chỉnh sửa'!B390 | B18: Khởi nghiệp | C18: ='Phân tích và chỉnh sửa'!B392 | D18: ='Phân tích và chỉnh sửa'!B393 | E18: ='Phân tích và chỉnh sửa'!B394 | F18: ='Phân tích và chỉnh sửa'!B395 | G18: ='Phân tích và chỉnh sửa'!B396 | H18: ='Phân tích và chỉnh sửa'!B397 | I18: ='Phân tích và chỉnh sửa'!B398 | J18: ='Phân tích và chỉnh sửa'!B399 | K18: ='Phân tích và chỉnh sửa'!B400 | L18: ='Phân tích và chỉnh sửa'!B401 | M18: ='Phân tích và chỉnh sửa'!B402
A19: ='Phân tích và chỉnh sửa'!B616 | B19: Khởi nghiệp | C19: ='Phân tích và chỉnh sửa'!B617 | D19: ='Phân tích và chỉnh sửa'!B605 | E19: ='Phân tích và chỉnh sửa'!B618 | F19: ='Phân tích và chỉnh sửa'!B619 | G19: ='Phân tích và chỉnh sửa'!B620 | H19: ='Phân tích và chỉnh sửa'!B621 | I19: ='Phân tích và chỉnh sửa'!B622 | J19: ='Phân tích và chỉnh sửa'!B623 | K19: ='Phân tích và chỉnh sửa'!B624 | L19: ='Phân tích và chỉnh sửa'!B625 | M19: ='Phân tích và chỉnh sửa'!B626
A20: Cuộc thi STARTUP ZONE | B20: Khởi nghiệp | M20: https://www.facebook.com/ClbNhanSuKhoiNghiep.ueh?locale=vi_VN
A21: ='Phân tích và chỉnh sửa'!B644 | B21: Khởi nghiệp | C21: ='Phân tích và chỉnh sửa'!B645 | D21: ='Phân tích và chỉnh sửa'!B633 | E21: ='Phân tích và chỉnh sửa'!B646 | F21: ='Phân tích và chỉnh sửa'!B647 | G21: ='Phân tích và chỉnh sửa'!B648 | H21: ='Phân tích và chỉnh sửa'!B637 | I21: ='Phân tích và chỉnh sửa'!B650 | J21: ='Phân tích và chỉnh sửa'!B651 | K21: ='Phân tích và chỉnh sửa'!B652 | L21: ='Phân tích và chỉnh sửa'!B653 | M21: ='Phân tích và chỉnh sửa'!B654
A22: ='Phân tích và chỉnh sửa'!B672 | B22: Khởi nghiệp | C22: ='Phân tích và chỉnh sửa'!B673 | D22: ='Phân tích và chỉnh sửa'!B661 | E22: ='Phân tích và chỉnh sửa'!B674 | F22: ='Phân tích và chỉnh sửa'!B675 | G22: ='Phân tích và chỉnh sửa'!B676 | H22: ='Phân tích và chỉnh sửa'!B677 | I22: ='Phân tích và chỉnh sửa'!B678 | J22: ='Phân tích và chỉnh sửa'!B679 | K22: ='Phân tích và chỉnh sửa'!B680 | L22: ='Phân tích và chỉnh sửa'!B681 | M22: ='Phân tích và chỉnh sửa'!B682
A23: ='Phân tích và chỉnh sửa'!B700 | B23: Khởi nghiệp | C23: ='Phân tích và chỉnh sửa'!B701 | D23: ='Phân tích và chỉnh sửa'!B689 | E23: ='Phân tích và chỉnh sửa'!B702 | F23: ='Phân tích và chỉnh sửa'!B703 | G23: ='Phân tích và chỉnh sửa'!B704 | H23: ='Phân tích và chỉnh sửa'!B705 | I23: ='Phân tích và chỉnh sửa'!B706 | J23: ='Phân tích và chỉnh sửa'!B707 | K23: ='Phân tích và chỉnh sửa'!B708 | L23: ='Phân tích và chỉnh sửa'!B709 | M23: ='Phân tích và chỉnh sửa'!B710
A24: ='Phân tích và chỉnh sửa'!B728 | B24: Khởi nghiệp | C24: ='Phân tích và chỉnh sửa'!B729 | D24: ='Phân tích và chỉnh sửa'!B717 | E24: ='Phân tích và chỉnh sửa'!B730 | F24: ='Phân tích và chỉnh sửa'!B731 | G24: ='Phân tích và chỉnh sửa'!B732 | H24: ='Phân tích và chỉnh sửa'!B733 | I24: ='Phân tích và chỉnh sửa'!B734 | J24: ='Phân tích và chỉnh sửa'!B735 | K24: ='Phân tích và chỉnh sửa'!B736 | L24: ='Phân tích và chỉnh sửa'!B737 | M24: ='Phân tích và chỉnh sửa'!B738
A25: ='Phân tích và chỉnh sửa'!B1858 | B25: Khởi nghiệp | C25: ='Phân tích và chỉnh sửa'!B1860 | D25: ='Phân tích và chỉnh sửa'!B1861 | E25: ='Phân tích và chỉnh sửa'!B1862 | F25: ='Phân tích và chỉnh sửa'!B1863 | G25: ='Phân tích và chỉnh sửa'!B1864 | H25: ='Phân tích và chỉnh sửa'!B1865 | I25: ='Phân tích và chỉnh sửa'!B1866 | J25: ='Phân tích và chỉnh sửa'!B1867 | K25: ='Phân tích và chỉnh sửa'!B1868 | L25: ='Phân tích và chỉnh sửa'!B1869 | M25: ='Phân tích và chỉnh sửa'!B1870
A26: ='Phân tích và chỉnh sửa'!B756 | B26: Khởi nghiệp | C26: ='Phân tích và chỉnh sửa'!B757 | D26: ='Phân tích và chỉnh sửa'!B745 | E26: ='Phân tích và chỉnh sửa'!B758 | F26: ='Phân tích và chỉnh sửa'!B759 | G26: ='Phân tích và chỉnh sửa'!B760 | H26: ='Phân tích và chỉnh sửa'!B761 | I26: ='Phân tích và chỉnh sửa'!B762 | J26: ='Phân tích và chỉnh sửa'!B763 | K26: ='Phân tích và chỉnh sửa'!B764 | L26: ='Phân tích và chỉnh sửa'!B765 | M26: ='Phân tích và chỉnh sửa'!B766
A27: ='Phân tích và chỉnh sửa'!B118 | B27: Khởi nghiệp | C27: ='Phân tích và chỉnh sửa'!B120 | D27: ='Phân tích và chỉnh sửa'!B121 | E27: ='Phân tích và chỉnh sửa'!B122 | F27: ='Phân tích và chỉnh sửa'!B123 | G27: ='Phân tích và chỉnh sửa'!B124 | H27: ='Phân tích và chỉnh sửa'!B125 | I27: ='Phân tích và chỉnh sửa'!B126 | J27: ='Phân tích và chỉnh sửa'!B127 | K27: ='Phân tích và chỉnh sửa'!B128 | L27: ='Phân tích và chỉnh sửa'!B129 | M27: ='Phân tích và chỉnh sửa'!B130
A28: ='Phân tích và chỉnh sửa'!B784 | B28: Khởi nghiệp | C28: ='Phân tích và chỉnh sửa'!B785 | D28: ='Phân tích và chỉnh sửa'!B773 | E28: ='Phân tích và chỉnh sửa'!B786 | F28: ='Phân tích và chỉnh sửa'!B787 | G28: ='Phân tích và chỉnh sửa'!B788 | H28: ='Phân tích và chỉnh sửa'!B789 | I28: ='Phân tích và chỉnh sửa'!B790 | J28: ='Phân tích và chỉnh sửa'!B791 | K28: ='Phân tích và chỉnh sửa'!B780 | L28: ='Phân tích và chỉnh sửa'!B793 | M28: ='Phân tích và chỉnh sửa'!B794
A29: ='Phân tích và chỉnh sửa'!B812 | B29: Khởi nghiệp | C29: ='Phân tích và chỉnh sửa'!B813 | D29: ='Phân tích và chỉnh sửa'!B801 | E29: ='Phân tích và chỉnh sửa'!B814 | F29: ='Phân tích và chỉnh sửa'!B815 | G29: ='Phân tích và chỉnh sửa'!B816 | H29: ='Phân tích và chỉnh sửa'!B817 | I29: ='Phân tích và chỉnh sửa'!B818 | J29: ='Phân tích và chỉnh sửa'!B819 | K29: ='Phân tích và chỉnh sửa'!B820 | L29: ='Phân tích và chỉnh sửa'!B821 | M29: ='Phân tích và chỉnh sửa'!B822
A30: ='Phân tích và chỉnh sửa'!B840 | B30: Khởi nghiệp | C30: ='Phân tích và chỉnh sửa'!B841 | D30: ='Phân tích và chỉnh sửa'!B829 | E30: ='Phân tích và chỉnh sửa'!B842 | F30: ='Phân tích và chỉnh sửa'!B843 | G30: ='Phân tích và chỉnh sửa'!B844 | H30: ='Phân tích và chỉnh sửa'!B845 | I30: ='Phân tích và chỉnh sửa'!B846 | J30: ='Phân tích và chỉnh sửa'!B847 | K30: ='Phân tích và chỉnh sửa'!B848 | L30: ='Phân tích và chỉnh sửa'!B849 | M30: ='Phân tích và chỉnh sửa'!B850
A31: ='Phân tích và chỉnh sửa'!B868 | B31: Khởi nghiệp | C31: ='Phân tích và chỉnh sửa'!B869 | D31: ='Phân tích và chỉnh sửa'!B857 | E31: ='Phân tích và chỉnh sửa'!B870 | F31: ='Phân tích và chỉnh sửa'!B871 | G31: ='Phân tích và chỉnh sửa'!B872 | H31: ='Phân tích và chỉnh sửa'!B873 | I31: ='Phân tích và chỉnh sửa'!B874 | J31: ='Phân tích và chỉnh sửa'!B875 | K31: ='Phân tích và chỉnh sửa'!B876 | L31: ='Phân tích và chỉnh sửa'!B877 | M31: ='Phân tích và chỉnh sửa'!B878
A32: ='Phân tích và chỉnh sửa'!B134 | B32: Khởi nghiệp | C32: ='Phân tích và chỉnh sửa'!B136 | D32: ='Phân tích và chỉnh sửa'!B137 | E32: ='Phân tích và chỉnh sửa'!B138 | F32: ='Phân tích và chỉnh sửa'!B139 | G32: ='Phân tích và chỉnh sửa'!B140 | H32: ='Phân tích và chỉnh sửa'!B141 | I32: ='Phân tích và chỉnh sửa'!B142 | J32: ='Phân tích và chỉnh sửa'!B143 | K32: ='Phân tích và chỉnh sửa'!B144 | L32: ='Phân tích và chỉnh sửa'!B145 | M32: ='Phân tích và chỉnh sửa'!B146
A33: ='Phân tích và chỉnh sửa'!B150 | B33: Khởi nghiệp | C33: ='Phân tích và chỉnh sửa'!B152 | D33: ='Phân tích và chỉnh sửa'!B153 | E33: ='Phân tích và chỉnh sửa'!B154 | F33: ='Phân tích và chỉnh sửa'!B155 | G33: ='Phân tích và chỉnh sửa'!B156 | H33: ='Phân tích và chỉnh sửa'!B157 | I33: ='Phân tích và chỉnh sửa'!B158 | J33: ='Phân tích và chỉnh sửa'!B159 | K33: ='Phân tích và chỉnh sửa'!B160 | L33: ='Phân tích và chỉnh sửa'!B161 | M33: ='Phân tích và chỉnh sửa'!B162
A34: ='Phân tích và chỉnh sửa'!B166 | B34: Khởi nghiệp | C34: ='Phân tích và chỉnh sửa'!B168 | D34: ='Phân tích và chỉnh sửa'!B169 | E34: ='Phân tích và chỉnh sửa'!B170 | F34: ='Phân tích và chỉnh sửa'!B171 | G34: ='Phân tích và chỉnh sửa'!B172 | H34: ='Phân tích và chỉnh sửa'!B173 | I34: ='Phân tích và chỉnh sửa'!B174 | J34: ='Phân tích và chỉnh sửa'!B175 | K34: ='Phân tích và chỉnh sửa'!B176 | L34: ='Phân tích và chỉnh sửa'!B177 | M34: ='Phân tích và chỉnh sửa'!B178
A35: ='Phân tích và chỉnh sửa'!B214 | B35: Khởi nghiệp | C35: ='Phân tích và chỉnh sửa'!B216 | D35: ='Phân tích và chỉnh sửa'!B217 | E35: ='Phân tích và chỉnh sửa'!B218 | F35: ='Phân tích và chỉnh sửa'!B219 | G35: ='Phân tích và chỉnh sửa'!B220 | H35: ='Phân tích và chỉnh sửa'!B221 | I35: ='Phân tích và chỉnh sửa'!B222 | J35: ='Phân tích và chỉnh sửa'!B223 | K35: ='Phân tích và chỉnh sửa'!B224 | L35: ='Phân tích và chỉnh sửa'!B225 | M35: ='Phân tích và chỉnh sửa'!B226
A36: ='Phân tích và chỉnh sửa'!B896 | B36: Business case | C36: ='Phân tích và chỉnh sửa'!B897 | D36: ='Phân tích và chỉnh sửa'!B885 | E36: ='Phân tích và chỉnh sửa'!B898 | F36: ='Phân tích và chỉnh sửa'!B899 | G36: ='Phân tích và chỉnh sửa'!B900 | H36: ='Phân tích và chỉnh sửa'!B901 | I36: ='Phân tích và chỉnh sửa'!B902 | J36: ='Phân tích và chỉnh sửa'!B903 | K36: ='Phân tích và chỉnh sửa'!B904 | L36: ='Phân tích và chỉnh sửa'!B905 | M36: ='Phân tích và chỉnh sửa'!B906
A37: ='Phân tích và chỉnh sửa'!B198 | B37: Business case | C37: ='Phân tích và chỉnh sửa'!B200 | D37: ='Phân tích và chỉnh sửa'!B201 | E37: ='Phân tích và chỉnh sửa'!B202 | F37: ='Phân tích và chỉnh sửa'!B203 | G37: ='Phân tích và chỉnh sửa'!B204 | H37: ='Phân tích và chỉnh sửa'!B205 | I37: ='Phân tích và chỉnh sửa'!B206 | J37: ='Phân tích và chỉnh sửa'!B207 | K37: ='Phân tích và chỉnh sửa'!B208 | L37: ='Phân tích và chỉnh sửa'!B209 | M37: ='Phân tích và chỉnh sửa'!B210
A38: ='Phân tích và chỉnh sửa'!B924 | B38: Business case | C38: ='Phân tích và chỉnh sửa'!B925 | D38: ='Phân tích và chỉnh sửa'!B913 | E38: ='Phân tích và chỉnh sửa'!B926 | F38: ='Phân tích và chỉnh sửa'!B927 | G38: ='Phân tích và chỉnh sửa'!B928 | H38: ='Phân tích và chỉnh sửa'!B929 | I38: ='Phân tích và chỉnh sửa'!B930 | J38: ='Phân tích và chỉnh sửa'!B931 | K38: ='Phân tích và chỉnh sửa'!B932 | L38: ='Phân tích và chỉnh sửa'!B933 | M38: ='Phân tích và chỉnh sửa'!B934
A39: ='Phân tích và chỉnh sửa'!B952 | B39: Business case | C39: ='Phân tích và chỉnh sửa'!B953 | D39: ='Phân tích và chỉnh sửa'!B941 | E39: ='Phân tích và chỉnh sửa'!B954 | F39: ='Phân tích và chỉnh sửa'!B955 | G39: ='Phân tích và chỉnh sửa'!B956 | H39: ='Phân tích và chỉnh sửa'!B957 | I39: ='Phân tích và chỉnh sửa'!B958 | J39: ='Phân tích và chỉnh sửa'!B959 | K39: ='Phân tích và chỉnh sửa'!B960 | L39: ='Phân tích và chỉnh sửa'!B961 | M39: ='Phân tích và chỉnh sửa'!B962
A40: ='Phân tích và chỉnh sửa'!B214 | B40: Business case | C40: ='Phân tích và chỉnh sửa'!B216 | D40: ='Phân tích và chỉnh sửa'!B217 | E40: ='Phân tích và chỉnh sửa'!B218 | F40: ='Phân tích và chỉnh sửa'!B219 | G40: ='Phân tích và chỉnh sửa'!B220 | H40: ='Phân tích và chỉnh sửa'!B221 | I40: ='Phân tích và chỉnh sửa'!B222 | J40: ='Phân tích và chỉnh sửa'!B223 | K40: ='Phân tích và chỉnh sửa'!B224 | L40: ='Phân tích và chỉnh sửa'!B225 | M40: ='Phân tích và chỉnh sửa'!B226
A41: ='Phân tích và chỉnh sửa'!B230 | B41: Business case | C41: ='Phân tích và chỉnh sửa'!B232 | D41: ='Phân tích và chỉnh sửa'!B233 | E41: ='Phân tích và chỉnh sửa'!B234 | F41: ='Phân tích và chỉnh sửa'!B235 | G41: ='Phân tích và chỉnh sửa'!B236 | H41: ='Phân tích và chỉnh sửa'!B237 | I41: ='Phân tích và chỉnh sửa'!B238 | J41: ='Phân tích và chỉnh sửa'!B239 | K41: ='Phân tích và chỉnh sửa'!B240 | L41: ='Phân tích và chỉnh sửa'!B241 | M41: ='Phân tích và chỉnh sửa'!B242
A42: ='Phân tích và chỉnh sửa'!B294 | B42: Business case | C42: ='Phân tích và chỉnh sửa'!B296 | D42: ='Phân tích và chỉnh sửa'!B297 | E42: ='Phân tích và chỉnh sửa'!B298 | F42: ='Phân tích và chỉnh sửa'!B299 | G42: ='Phân tích và chỉnh sửa'!B300 | H42: ='Phân tích và chỉnh sửa'!B301 | I42: ='Phân tích và chỉnh sửa'!B302 | J42: ='Phân tích và chỉnh sửa'!B303 | K42: ='Phân tích và chỉnh sửa'!B304 | L42: ='Phân tích và chỉnh sửa'!B305 | M42: ='Phân tích và chỉnh sửa'!B306
A43: ='Phân tích và chỉnh sửa'!B262 | B43: Business case | C43: ='Phân tích và chỉnh sửa'!B264 | D43: ='Phân tích và chỉnh sửa'!B265 | E43: ='Phân tích và chỉnh sửa'!B266 | F43: ='Phân tích và chỉnh sửa'!B267 | G43: ='Phân tích và chỉnh sửa'!B268 | H43: ='Phân tích và chỉnh sửa'!B269 | I43: ='Phân tích và chỉnh sửa'!B270 | J43: ='Phân tích và chỉnh sửa'!B271 | K43: ='Phân tích và chỉnh sửa'!B272 | L43: ='Phân tích và chỉnh sửa'!B273 | M43: ='Phân tích và chỉnh sửa'!B274
A44: ='Phân tích và chỉnh sửa'!B1106 | B44: Business case | C44: ='Phân tích và chỉnh sửa'!B1108 | D44: ='Phân tích và chỉnh sửa'!B1109 | E44: ='Phân tích và chỉnh sửa'!B1110 | F44: ='Phân tích và chỉnh sửa'!B1111 | G44: ='Phân tích và chỉnh sửa'!B1112 | H44: ='Phân tích và chỉnh sửa'!B1113 | I44: ='Phân tích và chỉnh sửa'!B1114 | J44: ='Phân tích và chỉnh sửa'!B1115 | K44: ='Phân tích và chỉnh sửa'!B1116 | L44: ='Phân tích và chỉnh sửa'!B1117 | M44: ='Phân tích và chỉnh sửa'!B1118
A45: ='Phân tích và chỉnh sửa'!B1122 | B45: Thương mại điện tử | C45: ='Phân tích và chỉnh sửa'!B1124 | D45: ='Phân tích và chỉnh sửa'!B1125 | E45: ='Phân tích và chỉnh sửa'!B1126 | F45: ='Phân tích và chỉnh sửa'!B1127 | G45: ='Phân tích và chỉnh sửa'!B1128 | H45: ='Phân tích và chỉnh sửa'!B1129 | I45: ='Phân tích và chỉnh sửa'!B1130 | J45: ='Phân tích và chỉnh sửa'!B1131 | K45: ='Phân tích và chỉnh sửa'!B1132 | L45: ='Phân tích và chỉnh sửa'!B1133 | M45: ='Phân tích và chỉnh sửa'!B1134
A46: ='Phân tích và chỉnh sửa'!B278 | B46: Thương mại điện tử | C46: ='Phân tích và chỉnh sửa'!B280 | D46: ='Phân tích và chỉnh sửa'!B281 | E46: ='Phân tích và chỉnh sửa'!B282 | F46: ='Phân tích và chỉnh sửa'!B283 | G46: ='Phân tích và chỉnh sửa'!B284 | H46: ='Phân tích và chỉnh sửa'!B285 | I46: ='Phân tích và chỉnh sửa'!B286 | J46: ='Phân tích và chỉnh sửa'!B287 | K46: ='Phân tích và chỉnh sửa'!B288 | L46: ='Phân tích và chỉnh sửa'!B289 | M46: ='Phân tích và chỉnh sửa'!B290
A47: ='Phân tích và chỉnh sửa'!B1874 | B47: Business case | C47: ='Phân tích và chỉnh sửa'!B1876 | D47: ='Phân tích và chỉnh sửa'!B1877 | E47: ='Phân tích và chỉnh sửa'!B1878 | F47: ='Phân tích và chỉnh sửa'!B1879 | G47: ='Phân tích và chỉnh sửa'!B1880 | H47: ='Phân tích và chỉnh sửa'!B1881 | I47: ='Phân tích và chỉnh sửa'!B1882 | J47: ='Phân tích và chỉnh sửa'!B1883 | K47: ='Phân tích và chỉnh sửa'!B1884 | L47: ='Phân tích và chỉnh sửa'!B1885 | M47: ='Phân tích và chỉnh sửa'!B1886
A48: ='Phân tích và chỉnh sửa'!B980 | B48: Business case | C48: ='Phân tích và chỉnh sửa'!B981 | D48: ='Phân tích và chỉnh sửa'!B969 | E48: ='Phân tích và chỉnh sửa'!B982 | F48: ='Phân tích và chỉnh sửa'!B983 | G48: ='Phân tích và chỉnh sửa'!B984 | H48: ='Phân tích và chỉnh sửa'!B985 | I48: ='Phân tích và chỉnh sửa'!B986 | J48: ='Phân tích và chỉnh sửa'!B987 | K48: ='Phân tích và chỉnh sửa'!B988 | L48: ='Phân tích và chỉnh sửa'!B989 | M48: ='Phân tích và chỉnh sửa'!B990
A49: ='Phân tích và chỉnh sửa'!B1008 | B49: MT&Young Talent | C49: ='Phân tích và chỉnh sửa'!B1009 | D49: ='Phân tích và chỉnh sửa'!B997 | E49: ='Phân tích và chỉnh sửa'!B1010 | F49: ='Phân tích và chỉnh sửa'!B1011 | G49: ='Phân tích và chỉnh sửa'!B1012 | H49: ='Phân tích và chỉnh sửa'!B1013 | I49: ='Phân tích và chỉnh sửa'!B1014 | J49: ='Phân tích và chỉnh sửa'!B1015 | K49: ='Phân tích và chỉnh sửa'!B1016 | L49: ='Phân tích và chỉnh sửa'!B1017 | M49: ='Phân tích và chỉnh sửa'!B1018
A50: ='Phân tích và chỉnh sửa'!B1036 | B50: MT&Young Talent | C50: ='Phân tích và chỉnh sửa'!B1037 | D50: ='Phân tích và chỉnh sửa'!B1025 | E50: ='Phân tích và chỉnh sửa'!B1038 | F50: ='Phân tích và chỉnh sửa'!B1039 | G50: ='Phân tích và chỉnh sửa'!B1028 | H50: ='Phân tích và chỉnh sửa'!B1029 | I50: ='Phân tích và chỉnh sửa'!B1042 | J50: ='Phân tích và chỉnh sửa'!B1043 | K50: ='Phân tích và chỉnh sửa'!B1044 | L50: ='Phân tích và chỉnh sửa'!B1045 | M50: ='Phân tích và chỉnh sửa'!B1046
A51: ='Phân tích và chỉnh sửa'!B1138 | B51: MT&Young Talent | C51: ='Phân tích và chỉnh sửa'!B1140 | D51: ='Phân tích và chỉnh sửa'!B1141 | E51: ='Phân tích và chỉnh sửa'!B1142 | F51: ='Phân tích và chỉnh sửa'!B1143 | G51: ='Phân tích và chỉnh sửa'!B1144 | H51: ='Phân tích và chỉnh sửa'!B1145 | I51: ='Phân tích và chỉnh sửa'!B1146 | J51: ='Phân tích và chỉnh sửa'!B1147 | K51: ='Phân tích và chỉnh sửa'!B1148 | L51: ='Phân tích và chỉnh sửa'!B1149 | M51: ='Phân tích và chỉnh sửa'!B1150
A52: ='Phân tích và chỉnh sửa'!B1154 | B52: MT&Young Talent | C52: ='Phân tích và chỉnh sửa'!B1156 | D52: ='Phân tích và chỉnh sửa'!B1157 | E52: ='Phân tích và chỉnh sửa'!B1158 | F52: ='Phân tích và chỉnh sửa'!B1159 | G52: ='Phân tích và chỉnh sửa'!B1160 | H52: ='Phân tích và chỉnh sửa'!B1161 | I52: ='Phân tích và chỉnh sửa'!B1162 | J52: ='Phân tích và chỉnh sửa'!B1163 | K52: ='Phân tích và chỉnh sửa'!B1164 | L52: ='Phân tích và chỉnh sửa'!B1165 | M52: ='Phân tích và chỉnh sửa'!B1166
A53: ='Phân tích và chỉnh sửa'!B310 | B53: MT&Young Talent | C53: ='Phân tích và chỉnh sửa'!B312 | D53: ='Phân tích và chỉnh sửa'!B313 | E53: ='Phân tích và chỉnh sửa'!B314 | F53: ='Phân tích và chỉnh sửa'!B315 | G53: ='Phân tích và chỉnh sửa'!B316 | H53: ='Phân tích và chỉnh sửa'!B317 | I53: ='Phân tích và chỉnh sửa'!B318 | J53: ='Phân tích và chỉnh sửa'!B319 | K53: ='Phân tích và chỉnh sửa'!B320 | L53: ='Phân tích và chỉnh sửa'!B321 | M53: ='Phân tích và chỉnh sửa'!B322
A54: ='Phân tích và chỉnh sửa'!B1170 | B54: MT&Young Talent | C54: ='Phân tích và chỉnh sửa'!B1172 | D54: ='Phân tích và chỉnh sửa'!B1173 | E54: ='Phân tích và chỉnh sửa'!B1174 | F54: ='Phân tích và chỉnh sửa'!B1175 | G54: ='Phân tích và chỉnh sửa'!B1176 | H54: ='Phân tích và chỉnh sửa'!B1177 | I54: ='Phân tích và chỉnh sửa'!B1178 | J54: ='Phân tích và chỉnh sửa'!B1179 | K54: ='Phân tích và chỉnh sửa'!B1180 | L54: ='Phân tích và chỉnh sửa'!B1181 | M54: ='Phân tích và chỉnh sửa'!B1182
A55: ='Phân tích và chỉnh sửa'!B1186 | B55: Tài chính | C55: ='Phân tích và chỉnh sửa'!B1188 | D55: ='Phân tích và chỉnh sửa'!B1189 | E55: ='Phân tích và chỉnh sửa'!B1190 | F55: ='Phân tích và chỉnh sửa'!B1191 | G55: ='Phân tích và chỉnh sửa'!B1192 | H55: ='Phân tích và chỉnh sửa'!B1193 | I55: ='Phân tích và chỉnh sửa'!B1194 | J55: ='Phân tích và chỉnh sửa'!B1195 | K55: ='Phân tích và chỉnh sửa'!B1196 | L55: ='Phân tích và chỉnh sửa'!B1197 | M55: ='Phân tích và chỉnh sửa'!B1198
A56: ='Phân tích và chỉnh sửa'!B1202 | B56: Tài chính | C56: ='Phân tích và chỉnh sửa'!B1204 | D56: ='Phân tích và chỉnh sửa'!B1205 | E56: ='Phân tích và chỉnh sửa'!B1206 | F56: ='Phân tích và chỉnh sửa'!B1207 | G56: ='Phân tích và chỉnh sửa'!B1208 | H56: ='Phân tích và chỉnh sửa'!B1209 | I56: ='Phân tích và chỉnh sửa'!B1210 | J56: ='Phân tích và chỉnh sửa'!B1211 | K56: ='Phân tích và chỉnh sửa'!B1212 | L56: ='Phân tích và chỉnh sửa'!B1213 | M56: ='Phân tích và chỉnh sửa'!B1214
A57: ='Phân tích và chỉnh sửa'!B1250 | B57: Tài chính | C57: ='Phân tích và chỉnh sửa'!B1252 | D57: ='Phân tích và chỉnh sửa'!B1253 | E57: ='Phân tích và chỉnh sửa'!B1254 | F57: ='Phân tích và chỉnh sửa'!B1255 | G57: ='Phân tích và chỉnh sửa'!B1256 | H57: ='Phân tích và chỉnh sửa'!B1257 | I57: ='Phân tích và chỉnh sửa'!B1258 | J57: ='Phân tích và chỉnh sửa'!B1259 | K57: ='Phân tích và chỉnh sửa'!B1260 | L57: ='Phân tích và chỉnh sửa'!B1261 | M57: ='Phân tích và chỉnh sửa'!B1262
A58: ='Phân tích và chỉnh sửa'!B1218 | B58: Tài chính | C58: ='Phân tích và chỉnh sửa'!B1220 | D58: ='Phân tích và chỉnh sửa'!B1221 | E58: ='Phân tích và chỉnh sửa'!B1222 | F58: ='Phân tích và chỉnh sửa'!B1223 | G58: ='Phân tích và chỉnh sửa'!B1224 | H58: ='Phân tích và chỉnh sửa'!B1225 | I58: ='Phân tích và chỉnh sửa'!B1226 | J58: ='Phân tích và chỉnh sửa'!B1227 | K58: ='Phân tích và chỉnh sửa'!B1228 | L58: ='Phân tích và chỉnh sửa'!B1229 | M58: ='Phân tích và chỉnh sửa'!B1230
A59: ='Phân tích và chỉnh sửa'!B1234 | B59: Tài chính | C59: ='Phân tích và chỉnh sửa'!B1236 | D59: ='Phân tích và chỉnh sửa'!B1237 | E59: ='Phân tích và chỉnh sửa'!B1238 | F59: ='Phân tích và chỉnh sửa'!B1239 | G59: ='Phân tích và chỉnh sửa'!B1240 | H59: ='Phân tích và chỉnh sửa'!B1241 | I59: ='Phân tích và chỉnh sửa'!B1242 | J59: ='Phân tích và chỉnh sửa'!B1243 | K59: ='Phân tích và chỉnh sửa'!B1244 | L59: ='Phân tích và chỉnh sửa'!B1245 | M59: ='Phân tích và chỉnh sửa'!B1246
A60: ='Phân tích và chỉnh sửa'!B1266 | B60: Tài chính | C60: ='Phân tích và chỉnh sửa'!B1268 | D60: ='Phân tích và chỉnh sửa'!B1269 | E60: ='Phân tích và chỉnh sửa'!B1270 | F60: ='Phân tích và chỉnh sửa'!B1271 | G60: ='Phân tích và chỉnh sửa'!B1272 | H60: ='Phân tích và chỉnh sửa'!B1273 | I60: ='Phân tích và chỉnh sửa'!B1274 | J60: ='Phân tích và chỉnh sửa'!B1275 | K60: ='Phân tích và chỉnh sửa'!B1276 | L60: ='Phân tích và chỉnh sửa'!B1277 | M60: ='Phân tích và chỉnh sửa'!B1278
A61: ='Phân tích và chỉnh sửa'!B1282 | B61: Tài chính | C61: ='Phân tích và chỉnh sửa'!B1284 | D61: ='Phân tích và chỉnh sửa'!B1285 | E61: ='Phân tích và chỉnh sửa'!B1286 | F61: ='Phân tích và chỉnh sửa'!B1287 | G61: ='Phân tích và chỉnh sửa'!B1288 | H61: ='Phân tích và chỉnh sửa'!B1289 | I61: ='Phân tích và chỉnh sửa'!B1290 | J61: ='Phân tích và chỉnh sửa'!B1291 | K61: ='Phân tích và chỉnh sửa'!B1292 | L61: ='Phân tích và chỉnh sửa'!B1293 | M61: ='Phân tích và chỉnh sửa'!B1294
A62: ='Phân tích và chỉnh sửa'!B1298 | B62: Tài chính | C62: ='Phân tích và chỉnh sửa'!B1300 | D62: ='Phân tích và chỉnh sửa'!B1301 | E62: ='Phân tích và chỉnh sửa'!B1302 | F62: ='Phân tích và chỉnh sửa'!B1303 | G62: ='Phân tích và chỉnh sửa'!B1304 | H62: ='Phân tích và chỉnh sửa'!B1305 | I62: ='Phân tích và chỉnh sửa'!B1306 | J62: ='Phân tích và chỉnh sửa'!B1307 | K62: ='Phân tích và chỉnh sửa'!B1308 | L62: ='Phân tích và chỉnh sửa'!B1309 | M62: ='Phân tích và chỉnh sửa'!B1310
A63: ='Phân tích và chỉnh sửa'!B1442 | B63: Tài chính | C63: ='Phân tích và chỉnh sửa'!B1444 | D63: ='Phân tích và chỉnh sửa'!B1445 | E63: ='Phân tích và chỉnh sửa'!B1446 | F63: ='Phân tích và chỉnh sửa'!B1447 | G63: ='Phân tích và chỉnh sửa'!B1448 | H63: ='Phân tích và chỉnh sửa'!B1449 | I63: ='Phân tích và chỉnh sửa'!B1450 | J63: ='Phân tích và chỉnh sửa'!B1451 | K63: ='Phân tích và chỉnh sửa'!B1452 | L63: ='Phân tích và chỉnh sửa'!B1453 | M63: ='Phân tích và chỉnh sửa'!B1454
A64: ='Phân tích và chỉnh sửa'!B326 | B64: Tài chính | C64: ='Phân tích và chỉnh sửa'!B328 | D64: ='Phân tích và chỉnh sửa'!B329 | E64: ='Phân tích và chỉnh sửa'!B330 | F64: ='Phân tích và chỉnh sửa'!B331 | G64: ='Phân tích và chỉnh sửa'!B332 | H64: ='Phân tích và chỉnh sửa'!B333 | I64: ='Phân tích và chỉnh sửa'!B334 | J64: ='Phân tích và chỉnh sửa'!B335 | K64: ='Phân tích và chỉnh sửa'!B336 | L64: ='Phân tích và chỉnh sửa'!B337 | M64: ='Phân tích và chỉnh sửa'!B338
A65: ='Phân tích và chỉnh sửa'!B1314 | B65: Tài chính | C65: ='Phân tích và chỉnh sửa'!B1316 | D65: ='Phân tích và chỉnh sửa'!B1317 | E65: ='Phân tích và chỉnh sửa'!B1318 | F65: ='Phân tích và chỉnh sửa'!B1319 | G65: ='Phân tích và chỉnh sửa'!B1320 | H65: ='Phân tích và chỉnh sửa'!B1321 | I65: ='Phân tích và chỉnh sửa'!B1322 | J65: ='Phân tích và chỉnh sửa'!B1323 | K65: ='Phân tích và chỉnh sửa'!B1324 | L65: ='Phân tích và chỉnh sửa'!B1325 | M65: ='Phân tích và chỉnh sửa'!B1326
A66: ='Phân tích và chỉnh sửa'!B358 | B66: Tài chính | C66: ='Phân tích và chỉnh sửa'!B360 | D66: ='Phân tích và chỉnh sửa'!B361 | E66: ='Phân tích và chỉnh sửa'!B362 | F66: ='Phân tích và chỉnh sửa'!B363 | G66: ='Phân tích và chỉnh sửa'!B364 | H66: ='Phân tích và chỉnh sửa'!B365 | I66: ='Phân tích và chỉnh sửa'!B366 | J66: ='Phân tích và chỉnh sửa'!B367 | K66: ='Phân tích và chỉnh sửa'!B368 | L66: ='Phân tích và chỉnh sửa'!B369 | M66: ='Phân tích và chỉnh sửa'!B370
A67: ='Phân tích và chỉnh sửa'!B1330 | B67: Tài chính | C67: ='Phân tích và chỉnh sửa'!B1332 | D67: ='Phân tích và chỉnh sửa'!B1333 | E67: ='Phân tích và chỉnh sửa'!B1334 | F67: ='Phân tích và chỉnh sửa'!B1335 | G67: ='Phân tích và chỉnh sửa'!B1336 | H67: ='Phân tích và chỉnh sửa'!B1337 | I67: ='Phân tích và chỉnh sửa'!B1338 | J67: ='Phân tích và chỉnh sửa'!B1339 | K67: ='Phân tích và chỉnh sửa'!B1340 | L67: ='Phân tích và chỉnh sửa'!B1341 | M67: ='Phân tích và chỉnh sửa'!B1342
A68: ='Phân tích và chỉnh sửa'!B1346 | B68: Tài chính | C68: ='Phân tích và chỉnh sửa'!B1348 | D68: ='Phân tích và chỉnh sửa'!B1349 | E68: ='Phân tích và chỉnh sửa'!B1350 | F68: ='Phân tích và chỉnh sửa'!B1351 | G68: ='Phân tích và chỉnh sửa'!B1352 | H68: ='Phân tích và chỉnh sửa'!B1353 | I68: ='Phân tích và chỉnh sửa'!B1354 | J68: ='Phân tích và chỉnh sửa'!B1355 | K68: ='Phân tích và chỉnh sửa'!B1356 | L68: ='Phân tích và chỉnh sửa'!B1357 | M68: ='Phân tích và chỉnh sửa'!B1358
A69: ='Phân tích và chỉnh sửa'!B358 | B69: Kế toán - Kiểm toán | C69: ='Phân tích và chỉnh sửa'!B360 | D69: ='Phân tích và chỉnh sửa'!B361 | E69: ='Phân tích và chỉnh sửa'!B362 | F69: ='Phân tích và chỉnh sửa'!B363 | G69: ='Phân tích và chỉnh sửa'!B364 | H69: ='Phân tích và chỉnh sửa'!B365 | I69: ='Phân tích và chỉnh sửa'!B366 | J69: ='Phân tích và chỉnh sửa'!B367 | K69: ='Phân tích và chỉnh sửa'!B368 | L69: ='Phân tích và chỉnh sửa'!B369 | M69: ='Phân tích và chỉnh sửa'!B370
A70: ='Phân tích và chỉnh sửa'!B1362 | B70: Kế toán - Kiểm toán | C70: ='Phân tích và chỉnh sửa'!B1364 | D70: ='Phân tích và chỉnh sửa'!B1365 | E70: ='Phân tích và chỉnh sửa'!B1366 | F70: ='Phân tích và chỉnh sửa'!B1367 | G70: ='Phân tích và chỉnh sửa'!B1368 | H70: ='Phân tích và chỉnh sửa'!B1369 | I70: ='Phân tích và chỉnh sửa'!B1370 | J70: ='Phân tích và chỉnh sửa'!B1371 | K70: ='Phân tích và chỉnh sửa'!B1372 | L70: ='Phân tích và chỉnh sửa'!B1373 | M70: ='Phân tích và chỉnh sửa'!B1374
A71: ='Phân tích và chỉnh sửa'!B1378 | B71: Kế toán - Kiểm toán | C71: ='Phân tích và chỉnh sửa'!B1380 | D71: ='Phân tích và chỉnh sửa'!B1381 | E71: ='Phân tích và chỉnh sửa'!B1382 | F71: ='Phân tích và chỉnh sửa'!B1383 | G71: ='Phân tích và chỉnh sửa'!B1384 | H71: ='Phân tích và chỉnh sửa'!B1385 | I71: ='Phân tích và chỉnh sửa'!B1386 | J71: ='Phân tích và chỉnh sửa'!B1387 | K71: ='Phân tích và chỉnh sửa'!B1388 | L71: ='Phân tích và chỉnh sửa'!B1389 | M71: ='Phân tích và chỉnh sửa'!B1390
A72: ='Phân tích và chỉnh sửa'!B1394 | B72: Luật | C72: ='Phân tích và chỉnh sửa'!B1396 | D72: ='Phân tích và chỉnh sửa'!B1397 | E72: ='Phân tích và chỉnh sửa'!B1398 | F72: ='Phân tích và chỉnh sửa'!B1399 | G72: ='Phân tích và chỉnh sửa'!B1400 | H72: ='Phân tích và chỉnh sửa'!B1401 | I72: ='Phân tích và chỉnh sửa'!B1402 | J72: ='Phân tích và chỉnh sửa'!B1403 | K72: ='Phân tích và chỉnh sửa'!B1404 | L72: ='Phân tích và chỉnh sửa'!B1405 | M72: ='Phân tích và chỉnh sửa'!B1406
A73: ='Phân tích và chỉnh sửa'!B1410 | B73: Luật | C73: ='Phân tích và chỉnh sửa'!B1412 | D73: ='Phân tích và chỉnh sửa'!B1413 | E73: ='Phân tích và chỉnh sửa'!B1414 | F73: ='Phân tích và chỉnh sửa'!B1415 | G73: ='Phân tích và chỉnh sửa'!B1416 | H73: ='Phân tích và chỉnh sửa'!B1417 | I73: ='Phân tích và chỉnh sửa'!B1418 | J73: ='Phân tích và chỉnh sửa'!B1419 | K73: ='Phân tích và chỉnh sửa'!B1420 | L73: ='Phân tích và chỉnh sửa'!B1421 | M73: ='Phân tích và chỉnh sửa'!B1422
A74: ='Phân tích và chỉnh sửa'!B1426 | B74: Luật | C74: ='Phân tích và chỉnh sửa'!B1428 | D74: ='Phân tích và chỉnh sửa'!B1429 | E74: ='Phân tích và chỉnh sửa'!B1430 | F74: ='Phân tích và chỉnh sửa'!B1431 | G74: ='Phân tích và chỉnh sửa'!B1432 | H74: ='Phân tích và chỉnh sửa'!B1433 | I74: ='Phân tích và chỉnh sửa'!B1434 | J74: ='Phân tích và chỉnh sửa'!B1435 | K74: ='Phân tích và chỉnh sửa'!B1436 | L74: ='Phân tích và chỉnh sửa'!B1437 | M74: ='Phân tích và chỉnh sửa'!B1438
A75: ='Phân tích và chỉnh sửa'!B374 | B75: HR | C75: ='Phân tích và chỉnh sửa'!B376 | D75: ='Phân tích và chỉnh sửa'!B377 | E75: ='Phân tích và chỉnh sửa'!B378 | F75: ='Phân tích và chỉnh sửa'!B379 | G75: ='Phân tích và chỉnh sửa'!B380 | H75: ='Phân tích và chỉnh sửa'!B381 | I75: ='Phân tích và chỉnh sửa'!B382 | J75: ='Phân tích và chỉnh sửa'!B383 | K75: ='Phân tích và chỉnh sửa'!B384 | L75: ='Phân tích và chỉnh sửa'!B385 | M75: ='Phân tích và chỉnh sửa'!B386
A76: ='Phân tích và chỉnh sửa'!B1458 | B76: HR | C76: ='Phân tích và chỉnh sửa'!B1460 | D76: ='Phân tích và chỉnh sửa'!B1461 | E76: ='Phân tích và chỉnh sửa'!B1462 | F76: ='Phân tích và chỉnh sửa'!B1463 | G76: ='Phân tích và chỉnh sửa'!B1464 | H76: ='Phân tích và chỉnh sửa'!B1465 | I76: ='Phân tích và chỉnh sửa'!B1466 | J76: ='Phân tích và chỉnh sửa'!B1467 | K76: ='Phân tích và chỉnh sửa'!B1468 | L76: ='Phân tích và chỉnh sửa'!B1469 | M76: ='Phân tích và chỉnh sửa'!B1470
A77: ='Phân tích và chỉnh sửa'!B1474 | B77: HR | C77: ='Phân tích và chỉnh sửa'!B1476 | D77: ='Phân tích và chỉnh sửa'!B1477 | E77: ='Phân tích và chỉnh sửa'!B1478 | F77: ='Phân tích và chỉnh sửa'!B1479 | G77: ='Phân tích và chỉnh sửa'!B1480 | H77: ='Phân tích và chỉnh sửa'!B1481 | I77: ='Phân tích và chỉnh sửa'!B1482 | J77: ='Phân tích và chỉnh sửa'!B1483 | K77: ='Phân tích và chỉnh sửa'!B1484 | L77: ='Phân tích và chỉnh sửa'!B1485 | M77: ='Phân tích và chỉnh sửa'!B1486
A78: ='Phân tích và chỉnh sửa'!B1490 | B78: MC | C78: ='Phân tích và chỉnh sửa'!B1492 | D78: ='Phân tích và chỉnh sửa'!B1493 | E78: ='Phân tích và chỉnh sửa'!B1494 | F78: ='Phân tích và chỉnh sửa'!B1495 | G78: ='Phân tích và chỉnh sửa'!B1496 | H78: ='Phân tích và chỉnh sửa'!B1497 | I78: ='Phân tích và chỉnh sửa'!B1498 | J78: ='Phân tích và chỉnh sửa'!B1499 | K78: ='Phân tích và chỉnh sửa'!B1500 | L78: ='Phân tích và chỉnh sửa'!B1501 | M78: ='Phân tích và chỉnh sửa'!B1502
A79: ='Phân tích và chỉnh sửa'!B1522 | B79: MC | C79: ='Phân tích và chỉnh sửa'!B1524 | D79: ='Phân tích và chỉnh sửa'!B1525 | E79: ='Phân tích và chỉnh sửa'!B1526 | F79: ='Phân tích và chỉnh sửa'!B1527 | G79: ='Phân tích và chỉnh sửa'!B1528 | H79: Giải thưởng chỉ kéo dài vài phút. | Nhưng cách một người sử dụng giải thưởng ấy | có thể kéo dài nhiều năm. | I79: ='Phân tích và chỉnh sửa'!B1530 | J79: ='Phân tích và chỉnh sửa'!B1531 | K79: ='Phân tích và chỉnh sửa'!B1532 | L79: ='Phân tích và chỉnh sửa'!B1533 | M79: ='Phân tích và chỉnh sửa'!B1534
A80: ='Phân tích và chỉnh sửa'!B1506 | B80: MC | C80: ='Phân tích và chỉnh sửa'!B1508 | D80: ='Phân tích và chỉnh sửa'!B1509 | E80: ='Phân tích và chỉnh sửa'!B1510 | F80: ='Phân tích và chỉnh sửa'!B1511 | G80: ='Phân tích và chỉnh sửa'!B1512 | H80: ='Phân tích và chỉnh sửa'!B1513 | I80: ='Phân tích và chỉnh sửa'!B1514 | J80: ='Phân tích và chỉnh sửa'!B1515 | K80: ='Phân tích và chỉnh sửa'!B1516 | L80: ='Phân tích và chỉnh sửa'!B1517 | M80: ='Phân tích và chỉnh sửa'!B1518
A81: ='Phân tích và chỉnh sửa'!B1586 | B81: MC | C81: ='Phân tích và chỉnh sửa'!B1588 | D81: ='Phân tích và chỉnh sửa'!B1589 | E81: ='Phân tích và chỉnh sửa'!B1590 | F81: ='Phân tích và chỉnh sửa'!B1591 | G81: ='Phân tích và chỉnh sửa'!B1592 | H81: ='Phân tích và chỉnh sửa'!B1593 | I81: ='Phân tích và chỉnh sửa'!B1594 | J81: ='Phân tích và chỉnh sửa'!B1595 | K81: ='Phân tích và chỉnh sửa'!B1596 | L81: ='Phân tích và chỉnh sửa'!B1597 | M81: ='Phân tích và chỉnh sửa'!B1598
A82: ='Phân tích và chỉnh sửa'!B1602 | B82: MC | C82: ='Phân tích và chỉnh sửa'!B1604 | D82: ='Phân tích và chỉnh sửa'!B1605 | E82: ='Phân tích và chỉnh sửa'!B1606 | F82: ='Phân tích và chỉnh sửa'!B1607 | G82: ='Phân tích và chỉnh sửa'!B1608 | H82: ='Phân tích và chỉnh sửa'!B1609 | I82: ='Phân tích và chỉnh sửa'!B1610 | J82: ='Phân tích và chỉnh sửa'!B1611 | K82: ='Phân tích và chỉnh sửa'!B1612 | L82: ='Phân tích và chỉnh sửa'!B1613 | M82: ='Phân tích và chỉnh sửa'!B1614
A83: ='Phân tích và chỉnh sửa'!B1538 | B83: MC | C83: ='Phân tích và chỉnh sửa'!B1540 | D83: ='Phân tích và chỉnh sửa'!B1541 | E83: ='Phân tích và chỉnh sửa'!B1542 | F83: ='Phân tích và chỉnh sửa'!B1543 | G83: ='Phân tích và chỉnh sửa'!B1544 | H83: ='Phân tích và chỉnh sửa'!B1545 | I83: ='Phân tích và chỉnh sửa'!B1546 | J83: ='Phân tích và chỉnh sửa'!B1547 | K83: ='Phân tích và chỉnh sửa'!B1548 | L83: ='Phân tích và chỉnh sửa'!B1549 | M83: ='Phân tích và chỉnh sửa'!B1550
A84: ='Phân tích và chỉnh sửa'!B1554 | B84: Tranh biện | C84: ='Phân tích và chỉnh sửa'!B1556 | D84: ='Phân tích và chỉnh sửa'!B1557 | E84: ='Phân tích và chỉnh sửa'!B1558 | F84: ='Phân tích và chỉnh sửa'!B1559 | G84: ='Phân tích và chỉnh sửa'!B1560 | H84: ='Phân tích và chỉnh sửa'!B1561 | I84: ='Phân tích và chỉnh sửa'!B1562 | J84: ='Phân tích và chỉnh sửa'!B1563 | K84: ='Phân tích và chỉnh sửa'!B1564 | L84: ='Phân tích và chỉnh sửa'!B1565 | M84: ='Phân tích và chỉnh sửa'!B1566
A85: ='Phân tích và chỉnh sửa'!B1570 | B85: Tranh biện | C85: ='Phân tích và chỉnh sửa'!B1572 | D85: ='Phân tích và chỉnh sửa'!B1573 | E85: ='Phân tích và chỉnh sửa'!B1574 | F85: ='Phân tích và chỉnh sửa'!B1575 | G85: ='Phân tích và chỉnh sửa'!B1576 | H85: ='Phân tích và chỉnh sửa'!B1577 | I85: ='Phân tích và chỉnh sửa'!B1578 | J85: ='Phân tích và chỉnh sửa'!B1579 | K85: ='Phân tích và chỉnh sửa'!B1580 | L85: ='Phân tích và chỉnh sửa'!B1581 | M85: ='Phân tích và chỉnh sửa'!B1582
A86: ='Phân tích và chỉnh sửa'!B1618 | B86: Hùng biện - diễn thuyết | C86: ='Phân tích và chỉnh sửa'!B1620 | D86: ='Phân tích và chỉnh sửa'!B1621 | E86: ='Phân tích và chỉnh sửa'!B1622 | F86: ='Phân tích và chỉnh sửa'!B1623 | G86: ='Phân tích và chỉnh sửa'!B1624 | H86: ='Phân tích và chỉnh sửa'!B1625 | I86: ='Phân tích và chỉnh sửa'!B1626 | J86: ='Phân tích và chỉnh sửa'!B1627 | K86: ='Phân tích và chỉnh sửa'!B1628 | L86: ='Phân tích và chỉnh sửa'!B1629 | M86: ='Phân tích và chỉnh sửa'!B1630
A87: ='Phân tích và chỉnh sửa'!B1634 | B87: Hùng biện - diễn thuyết | C87: ='Phân tích và chỉnh sửa'!B1636 | D87: ='Phân tích và chỉnh sửa'!B1637 | E87: ='Phân tích và chỉnh sửa'!B1638 | F87: ='Phân tích và chỉnh sửa'!B1639 | G87: ='Phân tích và chỉnh sửa'!B1640 | H87: ='Phân tích và chỉnh sửa'!B1641 | I87: ='Phân tích và chỉnh sửa'!B1642 | J87: ='Phân tích và chỉnh sửa'!B1643 | K87: ='Phân tích và chỉnh sửa'!B1644 | L87: ='Phân tích và chỉnh sửa'!B1645 | M87: ='Phân tích và chỉnh sửa'!B1646
A88: ='Phân tích và chỉnh sửa'!B1650 | B88: Hùng biện - diễn thuyết | C88: ='Phân tích và chỉnh sửa'!B1652 | D88: ='Phân tích và chỉnh sửa'!B1653 | E88: ='Phân tích và chỉnh sửa'!B1654 | F88: trực tiếp quyết định chủ nhân của ngôi vị cao nhất của Tôi | G88: ='Phân tích và chỉnh sửa'!B1656 | H88: quán quân cũng đã lộ diện trong sự ủng hộ và cổ vũ từ tất cả mọi người. Có lẽ trong mỗi chúng ta đều dành riêng cho Tôi Bản lĩnh một vị trí quan trọng, một tình cảm vô cùng đặc biệt. | I88: ='Phân tích và chỉnh sửa'!B1658 | J88: ='Phân tích và chỉnh sửa'!B1659 | K88: 10/08 | L88: ='Phân tích và chỉnh sửa'!B1661 | M88: ='Phân tích và chỉnh sửa'!B1662
A89: ='Phân tích và chỉnh sửa'!B1650 | B89: Hùng biện - diễn thuyết | C89: ='Phân tích và chỉnh sửa'!B1652 | D89: ='Phân tích và chỉnh sửa'!B1653 | E89: ='Phân tích và chỉnh sửa'!B1654 | F89: ='Phân tích và chỉnh sửa'!B1655 | G89: ='Phân tích và chỉnh sửa'!B1656 | H89: ='Phân tích và chỉnh sửa'!B1657 | I89: ='Phân tích và chỉnh sửa'!B1658 | J89: ='Phân tích và chỉnh sửa'!B1659 | K89: ='Phân tích và chỉnh sửa'!B1660 | L89: ='Phân tích và chỉnh sửa'!B1661 | M89: ='Phân tích và chỉnh sửa'!B1662
A90: VOICE MASTER - Nhà diễn thuyết tài ba | B90: Hùng biện - diễn thuyết | M90: https://www.facebook.com/profile.php?id=61558798243512&locale=vi_VN
A91: ='Phân tích và chỉnh sửa'!B1714 | B91: Hùng biện - diễn thuyết | C91: ='Phân tích và chỉnh sửa'!B1716 | D91: ='Phân tích và chỉnh sửa'!B1717 | E91: ='Phân tích và chỉnh sửa'!B1718 | F91: ='Phân tích và chỉnh sửa'!B1719 | G91: ='Phân tích và chỉnh sửa'!B1720 | H91: ='Phân tích và chỉnh sửa'!B1721 | I91: ='Phân tích và chỉnh sửa'!B1722 | J91: ='Phân tích và chỉnh sửa'!B1723 | K91: ='Phân tích và chỉnh sửa'!B1724 | L91: ='Phân tích và chỉnh sửa'!B1725 | M91: ='Phân tích và chỉnh sửa'!B1726
A92: ='Phân tích và chỉnh sửa'!B1522 | B92: Hùng biện - diễn thuyết | C92: ='Phân tích và chỉnh sửa'!B1524 | D92: ='Phân tích và chỉnh sửa'!B1525 | E92: ='Phân tích và chỉnh sửa'!B1526 | F92: ='Phân tích và chỉnh sửa'!B1527 | G92: ='Phân tích và chỉnh sửa'!B1528 | H92: ='Phân tích và chỉnh sửa'!B1529 | I92: ='Phân tích và chỉnh sửa'!B1530 | J92: ='Phân tích và chỉnh sửa'!B1531 | K92: ='Phân tích và chỉnh sửa'!B1532 | L92: ='Phân tích và chỉnh sửa'!B1533 | M92: ='Phân tích và chỉnh sửa'!B1534
A93: ='Phân tích và chỉnh sửa'!B1666 | B93: Phát thanh | C93: ='Phân tích và chỉnh sửa'!B1668 | D93: ='Phân tích và chỉnh sửa'!B1669 | E93: ='Phân tích và chỉnh sửa'!B1670 | F93: ='Phân tích và chỉnh sửa'!B1671 | G93: ='Phân tích và chỉnh sửa'!B1672 | H93: ='Phân tích và chỉnh sửa'!B1673 | I93: ='Phân tích và chỉnh sửa'!B1674 | J93: ='Phân tích và chỉnh sửa'!B1675 | K93: ='Phân tích và chỉnh sửa'!B1676 | L93: ='Phân tích và chỉnh sửa'!B1677 | M93: ='Phân tích và chỉnh sửa'!B1678
A94: ='Phân tích và chỉnh sửa'!B1682 | B94: Logistics | C94: ='Phân tích và chỉnh sửa'!B1684 | D94: ='Phân tích và chỉnh sửa'!B1685 | E94: ='Phân tích và chỉnh sửa'!B1686 | F94: ='Phân tích và chỉnh sửa'!B1687 | G94: ='Phân tích và chỉnh sửa'!B1688 | H94: ='Phân tích và chỉnh sửa'!B1689 | I94: ='Phân tích và chỉnh sửa'!B1690 | J94: ='Phân tích và chỉnh sửa'!B1691 | K94: ='Phân tích và chỉnh sửa'!B1692 | L94: ='Phân tích và chỉnh sửa'!B1693 | M94: ='Phân tích và chỉnh sửa'!B1694
A95: ='Phân tích và chỉnh sửa'!B1698 | B95: Logistics | C95: ='Phân tích và chỉnh sửa'!B1700 | D95: ='Phân tích và chỉnh sửa'!B1701 | E95: ='Phân tích và chỉnh sửa'!B1702 | F95: ='Phân tích và chỉnh sửa'!B1703 | G95: ='Phân tích và chỉnh sửa'!B1704 | H95: ='Phân tích và chỉnh sửa'!B1705 | I95: ='Phân tích và chỉnh sửa'!B1706 | J95: ='Phân tích và chỉnh sửa'!B1707 | K95: ='Phân tích và chỉnh sửa'!B1708 | L95: ='Phân tích và chỉnh sửa'!B1709 | M95: ='Phân tích và chỉnh sửa'!B1710
A96: ='Phân tích và chỉnh sửa'!B1730 | B96: Logistics | C96: ='Phân tích và chỉnh sửa'!B1732 | D96: ='Phân tích và chỉnh sửa'!B1733 | E96: ='Phân tích và chỉnh sửa'!B1734 | F96: ='Phân tích và chỉnh sửa'!B1735 | G96: ='Phân tích và chỉnh sửa'!B1736 | H96: ='Phân tích và chỉnh sửa'!B1737 | I96: ='Phân tích và chỉnh sửa'!B1738 | J96: ='Phân tích và chỉnh sửa'!B1739 | K96: ='Phân tích và chỉnh sửa'!B1740 | L96: ='Phân tích và chỉnh sửa'!B1741 | M96: ='Phân tích và chỉnh sửa'!B1742
A97: ='Phân tích và chỉnh sửa'!B1746 | B97: Logistics | C97: ='Phân tích và chỉnh sửa'!B1748 | D97: ='Phân tích và chỉnh sửa'!B1749 | E97: ='Phân tích và chỉnh sửa'!B1750 | F97: ='Phân tích và chỉnh sửa'!B1751 | G97: ='Phân tích và chỉnh sửa'!B1752 | H97: ='Phân tích và chỉnh sửa'!B1753 | I97: ='Phân tích và chỉnh sửa'!B1754 | J97: ='Phân tích và chỉnh sửa'!B1755 | K97: ='Phân tích và chỉnh sửa'!B1756 | L97: ='Phân tích và chỉnh sửa'!B1757 | M97: ='Phân tích và chỉnh sửa'!B1758
A98: ='Phân tích và chỉnh sửa'!B1762 | B98: Logistics | C98: ='Phân tích và chỉnh sửa'!B1764 | D98: ='Phân tích và chỉnh sửa'!B1765 | E98: ='Phân tích và chỉnh sửa'!B1766 | F98: ='Phân tích và chỉnh sửa'!B1767 | G98: ='Phân tích và chỉnh sửa'!B1768 | H98: ='Phân tích và chỉnh sửa'!B1769 | I98: ='Phân tích và chỉnh sửa'!B1770 | J98: ='Phân tích và chỉnh sửa'!B1771 | K98: ='Phân tích và chỉnh sửa'!B1772 | L98: ='Phân tích và chỉnh sửa'!B1773 | M98: ='Phân tích và chỉnh sửa'!B1774
A99: ='Phân tích và chỉnh sửa'!B1778 | B99: Data | C99: ='Phân tích và chỉnh sửa'!B1780 | D99: ='Phân tích và chỉnh sửa'!B1781 | E99: ='Phân tích và chỉnh sửa'!B1782 | F99: ='Phân tích và chỉnh sửa'!B1783 | G99: ='Phân tích và chỉnh sửa'!B1784 | H99: ='Phân tích và chỉnh sửa'!B1785 | I99: ='Phân tích và chỉnh sửa'!B1786 | J99: ='Phân tích và chỉnh sửa'!B1787 | K99: ='Phân tích và chỉnh sửa'!B1788 | L99: ='Phân tích và chỉnh sửa'!B1789 | M99: ='Phân tích và chỉnh sửa'!B1790
A100: ='Phân tích và chỉnh sửa'!B1794 | B100: Analysis | C100: ='Phân tích và chỉnh sửa'!B1796 | D100: ='Phân tích và chỉnh sửa'!B1797 | E100: ='Phân tích và chỉnh sửa'!B1798 | F100: ='Phân tích và chỉnh sửa'!B1799 | G100: ='Phân tích và chỉnh sửa'!B1800 | H100: ='Phân tích và chỉnh sửa'!B1801 | I100: ='Phân tích và chỉnh sửa'!B1802 | J100: ='Phân tích và chỉnh sửa'!B1803 | K100: ='Phân tích và chỉnh sửa'!B1804 | L100: ='Phân tích và chỉnh sửa'!B1805 | M100: ='Phân tích và chỉnh sửa'!B1806
...

Sheet Phân tích và chỉnh sửa
A1: DỮ LIỆU PHÂN TÍCH (CÓ THỂ CHỈNH SỬA TRỰC TIẾP VÀO TỪNG Ô):
A2: Chỉnh sửa sẽ tự động lưu khi chuyển tab | Giá trị ở cột 'Giá Trị Sẽ Ghi Vào File' sẽ TỰ ĐỘNG CẬP NHẬT sang trang 'Tổng hợp'
A4: 🏆 CUỘC THI: KHỞI NGHIỆP CÙNG KAWAI 2026 [Liên kết tự động hàng #2 ở trang 'Tổng hợp ']
A5: Tên Cột Trong Excel | B5: Giá Trị Sẽ Ghi Vào File | C5: Nội dung từ web | D5: Link bài viết | E5: Ngày đăng bài (nếu có) | F5: Vị trí liên kết trang Tổng hợp
A6: Tên cuộc thi | B6: Khởi nghiệp cùng Kawai 2026 | C6: Khởi nghiệp cùng Kawai 2026 | D6: https://kbs.tec-ftu.com/ | E6: — | F6: ='Tổng hợp '!A2
A7: Lĩnh vực | B7: Khởi nghiệp | C7: Khởi nghiệp / Đổi mới sáng tạo | D7: https://kbs.tec-ftu.com/ | E7: — | F7: ='Tổng hợp '!B2
A8: Đơn vị tổ chức | B8: CLB Nhà Doanh nghiệp Tương lai (TEC) - Trường Đại học Ngoại thương | C8: CLB Nhà Doanh nghiệp Tương lai (TEC) - Trường Đại học Ngoại thương | D8: https://kbs.tec-ftu.com/ | E8: — | F8: ='Tổng hợp '!C2
A9: Mô tả ngắn gọn | B9: Cuộc thi ý tưởng khởi nghiệp sáng tạo dành cho startup Việt Nam 18–25 tuổi trên toàn thế giới, do CLB Nhà Doanh nghiệp Tương lai (TEC FTU) tổ chức. Mùa thi thứ 21 với đêm chung kết chủ đề "Tinh Quang" – nơi top 5 đội xuất sắc nhất pitching trước ban giám khảo, quỹ đầu tư và doanh nghiệp. | C9: Cuộc thi ý tưởng khởi nghiệp sáng tạo dành cho startup Việt Nam 18–25 tuổi trên toàn thế giới, do CLB Nhà Doanh nghiệp Tương lai (TEC FTU) tổ chức. Mùa thi thứ 21 với đêm chung kết chủ đề "Tinh Quang" – nơi top 5 đội xuất sắc nhất pitching trước ban giám khảo, quỹ đầu tư và doanh nghiệp. | D9: https://kbs.tec-ftu.com/ | E9: — | F9: ='Tổng hợp '!D2
A10: Đối tượng tham gia | B10: Startup Việt Nam trong độ tuổi 18–25 trên toàn thế giới | C10: Startup Việt Nam trong độ tuổi 18–25 trên toàn thế giới | D10: https://kbs.tec-ftu.com/ | E10: — | F10: ='Tổng hợp '!E2
A11: Hình thức tham gia | B11: Hybrid - Team (1-5 người) | C11: Hybrid - Team (1-5 người) | D11: https://kbs.tec-ftu.com/ | E11: — | F11: ='Tổng hợp '!F2
A12: Cơ cấu vòng thi | B12: Cuộc thi gồm 3 vòng: Vòng 1 và Vòng 2 là các vòng thử thách thực chiến (chi tiết không được cung cấp trong bài đăng); Vòng 3 'Tinh Quang' là Đêm Chung kết với phần pitching của TOP 5 đội xuất sắc trước Ban giám khảo, diễn ra tại Cung Văn hóa Lao động Hữu nghị Việt Xô ngày 08/07/2026. | C12: Cuộc thi gồm 3 vòng: Vòng 1 và Vòng 2 là các vòng thử thách thực chiến (chi tiết không được cung cấp trong bài đăng); Vòng 3 'Tinh Quang' là Đêm Chung kết với phần pitching của TOP 5 đội xuất sắc trước Ban giám khảo, diễn ra tại Cung Văn hóa Lao động Hữu nghị Việt Xô ngày 08/07/2026. | D12: https://kbs.tec-ftu.com/ | E12: — | F12: ='Tổng hợp '!G2
A13: Cơ cấu giải thưởng | B13: Chưa công bố chi tiết; ngôi vị Quán quân mùa thi thứ 21 được trao tại Đêm Chung kết | C13: Chưa công bố chi tiết; ngôi vị Quán quân mùa thi thứ 21 được trao tại Đêm Chung kết | D13: https://kbs.tec-ftu.com/ | E13: — | F13: ='Tổng hợp '!H2
A14: Các mốc thời gian | B14: Vòng 1: Nộp hồ sơ & Ý tưởng ban đầu: Không rõ | Vòng 2: Thử thách thực chiến: Không rõ | Vòng 3 - Tinh Quang: Đêm Chung kết: 2026-07-08 | C14: Vòng 1: Nộp hồ sơ & Ý tưởng ban đầu: Không rõ | Vòng 2: Thử thách thực chiến: Không rõ | Vòng 3 - Tinh Quang: Đêm Chung kết: 2026-07-08 | D14: https://kbs.tec-ftu.com/ | E14: — | F14: ='Tổng hợp '!I2
A15: Mùa thi | B15: Mùa thi thứ 21 (2026) | C15: Mùa thi thứ 21 (2026) | D15: https://kbs.tec-ftu.com/ | E15: — | F15: ='Tổng hợp '!J2
A16: Deadline đăng ký | B16: 2026-07-08 | C16: 2026-07-08 | D16: https://kbs.tec-ftu.com/ | E16: — | F16: ='Tổng hợp '!K2
A17: Trạng thái | B17: Đã kết thúc | C17: Đã kết thúc | D17: https://kbs.tec-ftu.com/ | E17: — | F17: ='Tổng hợp '!L2
A18: Link nguồn chính thức | B18: https://kbs.tec-ftu.com/ | C18: https://kbs.tec-ftu.com/ | D18: https://kbs.tec-ftu.com/ | E18: — | F18: ='Tổng hợp '!M2
A19: Tên cuộc thi | B19: Khởi nghiệp cùng Kawai 2026 | C19: Khởi nghiệp cùng Kawai 2026 | D19: https://kbs.tec-ftu.com/ | E19: — | F19: ='Tổng hợp '!A2
A20: Lĩnh vực | B20: Khởi nghiệp | C20: Khởi nghiệp / Đổi mới sáng tạo | D20: https://kbs.tec-ftu.com/ | E20: — | F20: ='Tổng hợp '!B2
A21: Đơn vị tổ chức | B21: CLB Nhà Doanh nghiệp Tương lai (TEC) - Trường Đại học Ngoại thương | C21: CLB Nhà Doanh nghiệp Tương lai (TEC) - Trường Đại học Ngoại thương | D21: https://kbs.tec-ftu.com/ | E21: — | F21: ='Tổng hợp '!C2
A22: Đối tượng tham gia | B22: Startup Việt Nam trong độ tuổi 18–25 trên toàn thế giới | C22: Startup Việt Nam trong độ tuổi 18–25 trên toàn thế giới | D22: https://kbs.tec-ftu.com/ | E22: — | F22: ='Tổng hợp '!E2
A23: Hình thức tham gia | B23: Thi theo đội; nộp ý tưởng khởi nghiệp, trải qua các vòng thử thách thực chiến và pitching trực tiếp tại đêm chung kết | C23: Thi theo đội; nộp ý tưởng khởi nghiệp, trải qua các vòng thử thách thực chiến và pitching trực tiếp tại đêm chung kết | D23: https://kbs.tec-ftu.com/ | E23: — | F23: ='Tổng hợp '!F2
A24: Cơ cấu vòng thi | B24: Vòng 1; Vòng 2; Vòng 3 (Tinh Quang – Đêm Chung kết): Top 5 đội xuất sắc pitching trước Ban giám khảo | C24: Vòng 1; Vòng 2; Vòng 3 (Tinh Quang – Đêm Chung kết): Top 5 đội xuất sắc pitching trước Ban giám khảo | D24: https://kbs.tec-ftu.com/ | E24: — | F24: ='Tổng hợp '!G2
A25: Cơ cấu giải thưởng | B25: Chưa công bố chi tiết; ngôi vị Quán quân mùa thi thứ 21 được trao tại Đêm Chung kết | C25: Chưa công bố chi tiết; ngôi vị Quán quân mùa thi thứ 21 được trao tại Đêm Chung kết | D25: https://kbs.tec-ftu.com/ | E25: — | F25: ='Tổng hợp '!H2
A26: Các mốc thời gian | B26: Đêm Chung kết: 08/07/2026 tại Cung Văn hóa Lao động Hữu nghị Việt Xô, 91 Trần Hưng Đạo, Hoàn Kiếm, Hà Nội | C26: Đêm Chung kết: 08/07/2026 tại Cung Văn hóa Lao động Hữu nghị Việt Xô, 91 Trần Hưng Đạo, Hoàn Kiếm, Hà Nội | D26: https://kbs.tec-ftu.com/ | E26: — | F26: ='Tổng hợp '!I2
A27: Mùa thi | B27: Mùa thi thứ 21 (2026) | C27: Mùa thi thứ 21 (2026) | D27: https://kbs.tec-ftu.com/ | E27: — | F27: ='Tổng hợp '!J2
A28: Deadline đăng ký | C28: (Chưa có trích dẫn từ web) | D28: https://kbs.tec-ftu.com/ | E28: — | F28: ='Tổng hợp '!K2
A29: Trạng thái | B29: Đang mở đăng ký tham dự Đêm Chung kết (vòng 3) | C29: Đang mở đăng ký tham dự Đêm Chung kết (vòng 3) | D29: https://kbs.tec-ftu.com/ | E29: — | F29: ='Tổng hợp '!L2
A30: Link nguồn chính thức | B30: http://kbs.tec-ftu.com/ | C30: http://kbs.tec-ftu.com/ | D30: https://kbs.tec-ftu.com/ | E30: — | F30: ='Tổng hợp '!M2
D31: https://kbs.tec-ftu.com/
D32: https://kbs.tec-ftu.com/
D33: https://kbs.tec-ftu.com/
D34: https://kbs.tec-ftu.com/
A36: 🏆 CUỘC THI: KHỞI NGHIỆP TRẺ 2026 [Liên kết tự động hàng #4 ở trang 'Tổng hợp ']
A37: Tên Cột Trong Excel | B37: Giá Trị Sẽ Ghi Vào File | C37: Nội dung từ web | D37: Link bài viết | E37: Ngày đăng bài (nếu có) | F37: Vị trí liên kết trang Tổng hợp
A38: Tên cuộc thi | B38: Khởi Nghiệp Trẻ 2026 | C38: Khởi Nghiệp Trẻ 2026 | D38: https://bsc-aof.com/index.php/khoi-nghiep-tre-2026/ | E38: 23/09/2026 | F38: ='Tổng hợp '!A4
A39: Lĩnh vực | B39: Khởi nghiệp | C39: Khởi nghiệp / Kinh doanh | D39: https://bsc-aof.com/index.php/khoi-nghiep-tre-2026/ | E39: 23/09/2026 | F39: ='Tổng hợp '!B4
A40: Đơn vị tổ chức | B40: Câu lạc bộ Kỹ năng Kinh doanh (BSC) – Học viện Tài chính; hỗ trợ bởi Liên chi đoàn Khoa Tài chính Doanh nghiệp và Đoàn Thanh niên Học viện Tài chính | C40: Câu lạc bộ Kỹ năng Kinh doanh (BSC) – Học viện Tài chính; hỗ trợ bởi Liên chi đoàn Khoa Tài chính Doanh nghiệp và Đoàn Thanh niên Học viện Tài chính | D40: https://bsc-aof.com/index.php/khoi-nghiep-tre-2026/ | E40: 23/09/2026 | F40: ='Tổng hợp '!C4
A41: Mô tả ngắn gọn | B41: Cuộc thi sáng tạo ý tưởng khởi nghiệp dành cho sinh viên Học viện Tài chính, tiền thân là cuộc thi "Khởi nghiệp trong tôi", nhằm tìm kiếm và phát triển sinh viên có đam mê kinh doanh, khởi nghiệp. | C41: Cuộc thi sáng tạo ý tưởng khởi nghiệp dành cho sinh viên Học viện Tài chính, tiền thân là cuộc thi "Khởi nghiệp trong tôi", nhằm tìm kiếm và phát triển sinh viên có đam mê kinh doanh, khởi nghiệp. | D41: https://bsc-aof.com/index.php/khoi-nghiep-tre-2026/ | E41: 23/09/2026 | F41: ='Tổng hợp '!D4
A42: Đối tượng tham gia | B42: Sinh viên Học viện Tài chính | C42: Sinh viên Học viện Tài chính | D42: https://bsc-aof.com/index.php/khoi-nghiep-tre-2026/ | E42: 23/09/2026 | F42: ='Tổng hợp '!E4
A43: Hình thức tham gia | B43: Thi theo đội (có hỗ trợ ghép đội cho cá nhân hoặc đội thiếu thành viên) | C43: Thi theo đội (có hỗ trợ ghép đội cho cá nhân hoặc đội thiếu thành viên) | D43: https://bsc-aof.com/index.php/khoi-nghiep-tre-2026/ | E43: 23/09/2026 | F43: ='Tổng hợp '!F4
A44: Cơ cấu vòng thi | C44: (Chưa có trích dẫn từ web) | D44: https://bsc-aof.com/index.php/khoi-nghiep-tre-2026/ | E44: 23/09/2026 | F44: ='Tổng hợp '!G4
A45: Cơ cấu giải thưởng | C45: (Chưa có trích dẫn từ web) | D45: https://bsc-aof.com/index.php/khoi-nghiep-tre-2026/ | E45: 23/09/2026 | F45: ='Tổng hợp '!H4
A46: Các mốc thời gian | B46: Deadline nộp đề án: đã hết hạn (bộ đếm ngược về 00:00:00) | C46: Deadline nộp đề án: đã hết hạn (bộ đếm ngược về 00:00:00) | D46: https://bsc-aof.com/index.php/khoi-nghiep-tre-2026/ | E46: 23/09/2026 | F46: ='Tổng hợp '!I4
A47: Mùa thi | B47: 2026 | C47: 2026 | D47: https://bsc-aof.com/index.php/khoi-nghiep-tre-2026/ | E47: 23/09/2026 | F47: ='Tổng hợp '!J4
A48: Deadline đăng ký | C48: (Chưa có trích dẫn từ web) | D48: https://bsc-aof.com/index.php/khoi-nghiep-tre-2026/ | E48: 23/09/2026 | F48: ='Tổng hợp '!K4
A49: Trạng thái | B49: Đã hết hạn nộp đề án | C49: Đã hết hạn nộp đề án | D49: https://bsc-aof.com/index.php/khoi-nghiep-tre-2026/ | E49: 23/09/2026 | F49: ='Tổng hợp '!L4
A50: Link nguồn chính thức | B50: https://bsc-aof.com/index.php/khoi-nghiep-tre-2026/ | C50: https://bsc-aof.com/index.php/khoi-nghiep-tre-2026/ | D50: https://bsc-aof.com/index.php/khoi-nghiep-tre-2026/ | E50: 23/09/2026 | F50: ='Tổng hợp '!M4
A52: 🏆 CUỘC THI: CUỘC THI KHỞI NGHIỆP SÁNG TẠO ĐHQGHN – RND TO STARTUP 2026 [Liên kết tự động hàng #9 ở trang 'Tổng hợp ']
A53: Tên Cột Trong Excel | B53: Giá Trị Sẽ Ghi Vào File | C53: Nội dung từ web | D53: Link bài viết | E53: Ngày đăng bài (nếu có) | F53: Vị trí liên kết trang Tổng hợp
A54: Tên cuộc thi | B54: Cuộc thi Khởi nghiệp Sáng tạo ĐHQGHN – RnD To Startup 2026 | C54: Cuộc thi Khởi nghiệp Sáng tạo ĐHQGHN – RnD To Startup 2026 | D54: https://visi.vnu.edu.vn/dich-vu/rnd-to-startup/ | E54: 30/09/2026 | F54: ='Tổng hợp '!A9
A55: Lĩnh vực | B55: Khởi nghiệp | C55: Khởi nghiệp & Đổi mới sáng tạo (8 nhóm lĩnh vực: Y tế & sức khỏe, Nông nghiệp & thực phẩm, Môi trường & phát triển bền vững, Công nghiệp/kỹ thuật/robotics, Giáo dục, Tài chính & kinh tế số, Văn hóa/sáng tạo/xã hội, Công nghệ thông tin & chuyển đổi số) | D55: https://visi.vnu.edu.vn/dich-vu/rnd-to-startup/ | E55: 30/09/2026 | F55: ='Tổng hợp '!B9
A56: Đơn vị tổ chức | B56: Vườn ươm Khởi nghiệp Đổi mới Sáng tạo ĐHQGHN (VISI), Trung tâm Chuyển giao Tri thức và Hỗ trợ Khởi nghiệp, Sunwah Innovations (Việt Nam) – do Đại học Quốc gia Hà Nội chỉ đạo | C56: Vườn ươm Khởi nghiệp Đổi mới Sáng tạo ĐHQGHN (VISI), Trung tâm Chuyển giao Tri thức và Hỗ trợ Khởi nghiệp, Sunwah Innovations (Việt Nam) – do Đại học Quốc gia Hà Nội chỉ đạo | D56: https://visi.vnu.edu.vn/dich-vu/rnd-to-startup/ | E56: 30/09/2026 | F56: ='Tổng hợp '!C9
A57: Mô tả ngắn gọn | B57: Cuộc thi tìm kiếm ý tưởng, sáng chế và dự án công nghệ có tiềm năng thương mại hóa trong học sinh, sinh viên, học viên cao học, nghiên cứu sinh và du học sinh Việt Nam; kết hợp đào tạo, mentoring và ươm tạo qua 4 vòng thi. | C57: Cuộc thi tìm kiếm ý tưởng, sáng chế và dự án công nghệ có tiềm năng thương mại hóa trong học sinh, sinh viên, học viên cao học, nghiên cứu sinh và du học sinh Việt Nam; kết hợp đào tạo, mentoring và ươm tạo qua 4 vòng thi. | D57: https://visi.vnu.edu.vn/dich-vu/rnd-to-startup/ | E57: 30/09/2026 | F57: ='Tổng hợp '!D9
A58: Đối tượng tham gia | B58: Học sinh, sinh viên, học viên cao học, nghiên cứu sinh và du học sinh Việt Nam trên cả nước | C58: Học sinh, sinh viên, học viên cao học, nghiên cứu sinh và du học sinh Việt Nam trên cả nước | D58: https://visi.vnu.edu.vn/dich-vu/rnd-to-startup/ | E58: 30/09/2026 | F58: ='Tổng hợp '!E9
A59: Hình thức tham gia | B59: Thi theo đội (tối đa 5 thành viên); 2 bảng: Bảng Ý tưởng và Bảng Dự án; nộp hồ sơ theo mẫu kèm Pitch Deck 12–15 slide và video giới thiệu tối đa 3 phút | C59: Thi theo đội (tối đa 5 thành viên); 2 bảng: Bảng Ý tưởng và Bảng Dự án; nộp hồ sơ theo mẫu kèm Pitch Deck 12–15 slide và video giới thiệu tối đa 3 phút | D59: https://visi.vnu.edu.vn/dich-vu/rnd-to-startup/ | E59: 30/09/2026 | F59: ='Tổng hợp '!F9
A60: Cơ cấu vòng thi | B60: 4 vòng: (1) Khởi nguồn – Sơ khảo hồ sơ, chọn Top 50; (2) Kiến tạo – 4 workshop, chọn Top 20; (3) Bứt phá – Bán kết pitching trực tiếp, chọn Top 10; (4) Toả sáng – Chung kết Demo Day | C60: 4 vòng: (1) Khởi nguồn – Sơ khảo hồ sơ, chọn Top 50; (2) Kiến tạo – 4 workshop, chọn Top 20; (3) Bứt phá – Bán kết pitching trực tiếp, chọn Top 10; (4) Toả sáng – Chung kết Demo Day | D60: https://visi.vnu.edu.vn/dich-vu/rnd-to-startup/ | E60: 30/09/2026 | F60: ='Tổng hợp '!G9
A61: Cơ cấu giải thưởng | B61: 11 giải + 1 suất ươm tạo VISI. Giải Nhất (×2, mỗi bảng 1): 30 triệu + Cúp + Giấy CN + Gói ươm tạo 2 tỷ đồng + Mentor 1:1 + kết nối DN/NĐT. Giải Nhì: 2 triệu + Giấy CN + mentor chuyên môn + kết nối đối tác. Giải Ba: Giấy CN + cơ hội tiền ươm tạo. Giải KK: Giấy CN + hỗ trợ cố vấn. Giải People's Choice: 1 giải chung 2 bảng. | C61: 11 giải + 1 suất ươm tạo VISI. Giải Nhất (×2, mỗi bảng 1): 30 triệu + Cúp + Giấy CN + Gói ươm tạo 2 tỷ đồng + Mentor 1:1 + kết nối DN/NĐT. Giải Nhì: 2 triệu + Giấy CN + mentor chuyên môn + kết nối đối tác. Giải Ba: Giấy CN + cơ hội tiền ươm tạo. Giải KK: Giấy CN + hỗ trợ cố vấn. Giải People's Choice: 1 giải chung 2 bảng. | D61: https://visi.vnu.edu.vn/dich-vu/rnd-to-startup/ | E61: 30/09/2026 | F61: ='Tổng hợp '!H9
A62: Các mốc thời gian | B62: 01/08–30/09/2026: Phát động & nhận hồ sơ | 01/10–10/10/2026: Chấm Sơ khảo, chọn Top 50 | 11/10–31/10/2026: 4 workshop đào tạo | 01/11–08/11/2026: Chấm Vòng 2, chọn Top 20 | 15/11/2026: Mentoring 1:1 | 16/11–22/11/2026: Bán kết, chọn Top 10 | 29/11/2026: Mentoring 1:1 | Tuần 2 tháng 12/2026: Chung kết – Demo Day | C62: 01/08–30/09/2026: Phát động & nhận hồ sơ | 01/10–10/10/2026: Chấm Sơ khảo, chọn Top 50 | 11/10–31/10/2026: 4 workshop đào tạo | 01/11–08/11/2026: Chấm Vòng 2, chọn Top 20 | 15/11/2026: Mentoring 1:1 | 16/11–22/11/2026: Bán kết, chọn Top 10 | 29/11/2026: Mentoring 1:1 | Tuần 2 tháng 12/2026: Chung kết – Demo Day | D62: https://visi.vnu.edu.vn/dich-vu/rnd-to-startup/ | E62: 30/09/2026 | F62: ='Tổng hợp '!I9
A63: Mùa thi | B63: 2026 | C63: 2026 | D63: https://visi.vnu.edu.vn/dich-vu/rnd-to-startup/ | E63: 30/09/2026 | F63: ='Tổng hợp '!J9
A64: Deadline đăng ký | B64: 30/09/2026 | C64: 30/09/2026 | D64: https://visi.vnu.edu.vn/dich-vu/rnd-to-startup/ | E64: 30/09/2026 | F64: ='Tổng hợp '!K9
A65: Trạng thái | B65: Đang mở đăng ký | C65: Đang mở đăng ký | D65: https://visi.vnu.edu.vn/dich-vu/rnd-to-startup/ | E65: 30/09/2026 | F65: ='Tổng hợp '!L9
A66: Link nguồn chính thức | B66: https://visi.vnu.edu.vn/dich-vu/rnd-to-startup/ | C66: https://visi.vnu.edu.vn/dich-vu/rnd-to-startup/ | D66: https://visi.vnu.edu.vn/dich-vu/rnd-to-startup/ | E66: 30/09/2026 | F66: ='Tổng hợp '!M9
A68: 🏆 CUỘC THI: STARTUP RUNWAY [Liên kết tự động hàng #10 ở trang 'Tổng hợp ']
A69: Tên Cột Trong Excel | B69: Giá Trị Sẽ Ghi Vào File | C69: Nội dung từ web | D69: Link bài viết | E69: Ngày đăng bài (nếu có) | F69: Vị trí liên kết trang Tổng hợp
A70: Tên cuộc thi | B70: Startup Runway | C70: Startup Runway | D70: http://due.udn.vn/vi-vn/startuprunway | E70: 24/08/2025 | F70: ='Tổng hợp '!A10
A71: Lĩnh vực | B71: Khởi nghiệp | C71: Khởi nghiệp, Đổi mới sáng tạo | D71: http://due.udn.vn/vi-vn/startuprunway | E71: 24/08/2025 | F71: ='Tổng hợp '!B10
A72: Đơn vị tổ chức | B72: Trường Đại học Kinh tế - Đại học Đà Nẵng | C72: Trường Đại học Kinh tế - Đại học Đà Nẵng | D72: http://due.udn.vn/vi-vn/startuprunway | E72: 24/08/2025 | F72: ='Tổng hợp '!C10
A73: Mô tả ngắn gọn | B73: Cuộc thi khởi nghiệp thường niên dành cho sinh viên, kết hợp đào tạo kiến thức khởi nghiệp, workshop và chuỗi vòng thi ý tưởng khởi nghiệp đổi mới sáng tạo. | C73: Cuộc thi khởi nghiệp thường niên dành cho sinh viên, kết hợp đào tạo kiến thức khởi nghiệp, workshop và chuỗi vòng thi ý tưởng khởi nghiệp đổi mới sáng tạo. | D73: http://due.udn.vn/vi-vn/startuprunway | E73: 24/08/2025 | F73: ='Tổng hợp '!D10
A74: Đối tượng tham gia | C74: (Chưa có trích dẫn từ web) | D74: http://due.udn.vn/vi-vn/startuprunway | E74: 24/08/2025 | F74: ='Tổng hợp '!E10
A75: Hình thức tham gia | C75: (Chưa có trích dẫn từ web) | D75: http://due.udn.vn/vi-vn/startuprunway | E75: 24/08/2025 | F75: ='Tổng hợp '!F10
A76: Cơ cấu vòng thi | B76: Vòng loại, Vòng 01, Vòng 02, Vòng 03, Chung kết | C76: Vòng loại, Vòng 01, Vòng 02, Vòng 03, Chung kết | D76: http://due.udn.vn/vi-vn/startuprunway | E76: 24/08/2025 | F76: ='Tổng hợp '!G10
A77: Cơ cấu giải thưởng | C77: (Chưa có trích dẫn từ web) | D77: http://due.udn.vn/vi-vn/startuprunway | E77: 24/08/2025 | F77: ='Tổng hợp '!H10
A78: Các mốc thời gian | B78: 24/08/2025: Ngày hội Khởi nghiệp đổi mới sáng tạo và Chung kết Startup Runway 2025 | C78: 24/08/2025: Ngày hội Khởi nghiệp đổi mới sáng tạo và Chung kết Startup Runway 2025 | D78: http://due.udn.vn/vi-vn/startuprunway | E78: 24/08/2025 | F78: ='Tổng hợp '!I10
A79: Mùa thi | B79: Startup Runway 2025 | C79: Startup Runway 2025 | D79: http://due.udn.vn/vi-vn/startuprunway | E79: 24/08/2025 | F79: ='Tổng hợp '!J10
A80: Deadline đăng ký | C80: (Chưa có trích dẫn từ web) | D80: http://due.udn.vn/vi-vn/startuprunway | E80: 24/08/2025 | F80: ='Tổng hợp '!K10
A81: Trạng thái | B81: Đã kết thúc (mùa 2025) | C81: Đã kết thúc (mùa 2025) | D81: http://due.udn.vn/vi-vn/startuprunway | E81: 24/08/2025 | F81: ='Tổng hợp '!L10
A82: Link nguồn chính thức | B82: http://due.udn.vn/vi-vn/startuprunway | C82: http://due.udn.vn/vi-vn/startuprunway | D82: http://due.udn.vn/vi-vn/startuprunway | E82: 24/08/2025 | F82: ='Tổng hợp '!M10
A84: 🏆 CUỘC THI: CUỘC THI KHỞI NGHIỆP RA KHƠI 2026 [Liên kết tự động hàng #11 ở trang 'Tổng hợp ']
A85: Tên Cột Trong Excel | B85: Giá Trị Sẽ Ghi Vào File | C85: Nội dung từ web | D85: Link bài viết | E85: Ngày đăng bài (nếu có) | F85: Vị trí liên kết trang Tổng hợp
A86: Tên cuộc thi | B86: Cuộc thi Khởi nghiệp Ra Khơi 2026 | C86: Cuộc thi Khởi nghiệp Ra Khơi 2026 | D86: https://rakhoi.vlu.edu.vn/ | E86: Bảng Sinh viên: 23h59 ngày 20/03/2026; Bảng Học sinh: 23h59 ngày 26/03/2026 | F86: ='Tổng hợp '!A11
A87: Lĩnh vực | B87: Khởi nghiệp | C87: Khởi nghiệp, Đổi mới sáng tạo, Kinh doanh bền vững (ESG, Kinh tế xanh – Kinh tế tuần hoàn) | D87: https://rakhoi.vlu.edu.vn/ | E87: Bảng Sinh viên: 23h59 ngày 20/03/2026; Bảng Học sinh: 23h59 ngày 26/03/2026 | F87: ='Tổng hợp '!B11
A88: Đơn vị tổ chức | B88: Trường Đại học Văn Lang (Khoa Quản trị Kinh doanh) | C88: Trường Đại học Văn Lang (Khoa Quản trị Kinh doanh) | D88: https://rakhoi.vlu.edu.vn/ | E88: Bảng Sinh viên: 23h59 ngày 20/03/2026; Bảng Học sinh: 23h59 ngày 26/03/2026 | F88: ='Tổng hợp '!C11
A89: Mô tả ngắn gọn | B89: Cuộc thi khởi nghiệp dành cho học sinh THPT và sinh viên, nhằm khơi dậy tinh thần đổi mới sáng tạo và tư duy kinh doanh bền vững, gắn với giải quyết vấn đề thực tiễn địa phương và xã hội. | C89: Cuộc thi khởi nghiệp dành cho học sinh THPT và sinh viên, nhằm khơi dậy tinh thần đổi mới sáng tạo và tư duy kinh doanh bền vững, gắn với giải quyết vấn đề thực tiễn địa phương và xã hội. | D89: https://rakhoi.vlu.edu.vn/ | E89: Bảng Sinh viên: 23h59 ngày 20/03/2026; Bảng Học sinh: 23h59 ngày 26/03/2026 | F89: ='Tổng hợp '!D11
A90: Đối tượng tham gia | B90: Bảng 1 (Future Founders): Học sinh THPT tại TP. HCM; Bảng 2 (Startup Pioneers): Sinh viên Đại học, Cao đẳng | C90: Bảng 1 (Future Founders): Học sinh THPT tại TP. HCM; Bảng 2 (Startup Pioneers): Sinh viên Đại học, Cao đẳng | D90: https://rakhoi.vlu.edu.vn/ | E90: Bảng Sinh viên: 23h59 ngày 20/03/2026; Bảng Học sinh: 23h59 ngày 26/03/2026 | F90: ='Tổng hợp '!E11
A91: Hình thức tham gia | B91: Thi nhóm (tối đa 05 thành viên/nhóm); nộp hồ sơ online hoặc trực tiếp tại Văn phòng Khoa QTKD | C91: Thi nhóm (tối đa 05 thành viên/nhóm); nộp hồ sơ online hoặc trực tiếp tại Văn phòng Khoa QTKD | D91: https://rakhoi.vlu.edu.vn/ | E91: Bảng Sinh viên: 23h59 ngày 20/03/2026; Bảng Học sinh: 23h59 ngày 26/03/2026 | F91: ='Tổng hợp '!F11
A92: Cơ cấu vòng thi | B92: Vòng 1 – Sơ khảo (01/4–20/4/2026): Training, Coaching, chấm chọn Top 20; Vòng 2 – Demo Day (22/4–30/4/2026): Trình bày trực tiếp, chọn Top đội chung kết; Vòng 3 – Chung kết (04/5–23/5/2026): Hoàn thiện & nộp hồ sơ kêu gọi đầu tư | C92: Vòng 1 – Sơ khảo (01/4–20/4/2026): Training, Coaching, chấm chọn Top 20; Vòng 2 – Demo Day (22/4–30/4/2026): Trình bày trực tiếp, chọn Top đội chung kết; Vòng 3 – Chung kết (04/5–23/5/2026): Hoàn thiện & nộp hồ sơ kêu gọi đầu tư | D92: https://rakhoi.vlu.edu.vn/ | E92: Bảng Sinh viên: 23h59 ngày 20/03/2026; Bảng Học sinh: 23h59 ngày 26/03/2026 | F92: ='Tổng hợp '!G11
A93: Cơ cấu giải thưởng | B93: Bảng Học sinh: Nhất 10tr, Nhì 5tr, Ba 3tr (x2), KK 1tr (x4). Bảng Sinh viên: Nhất 20tr, Nhì 10tr, Ba 6tr (x2), KK 3tr (x2), Tiềm Năng 2tr (x2). Tất cả kèm kỷ niệm chương, giấy khen, giấy CN. Tổng giải thưởng hơn 70 triệu VNĐ. | C93: Bảng Học sinh: Nhất 10tr, Nhì 5tr, Ba 3tr (x2), KK 1tr (x4). Bảng Sinh viên: Nhất 20tr, Nhì 10tr, Ba 6tr (x2), KK 3tr (x2), Tiềm Năng 2tr (x2). Tất cả kèm kỷ niệm chương, giấy khen, giấy CN. Tổng giải thưởng hơn 70 triệu VNĐ. | D93: https://rakhoi.vlu.edu.vn/ | E93: Bảng Sinh viên: 23h59 ngày 20/03/2026; Bảng Học sinh: 23h59 ngày 26/03/2026 | F93: ='Tổng hợp '!H11
A94: Các mốc thời gian | B94: Deadline nộp hồ sơ Bảng Sinh viên: 23h59 ngày 20/03/2026; Deadline nộp hồ sơ Bảng Học sinh: 23h59 ngày 26/03/2026; Sơ khảo: 01/4–20/4/2026; Demo Day: 22/4–30/4/2026; Chung kết: 04/5–23/5/2026 | C94: Deadline nộp hồ sơ Bảng Sinh viên: 23h59 ngày 20/03/2026; Deadline nộp hồ sơ Bảng Học sinh: 23h59 ngày 26/03/2026; Sơ khảo: 01/4–20/4/2026; Demo Day: 22/4–30/4/2026; Chung kết: 04/5–23/5/2026 | D94: https://rakhoi.vlu.edu.vn/ | E94: Bảng Sinh viên: 23h59 ngày 20/03/2026; Bảng Học sinh: 23h59 ngày 26/03/2026 | F94: ='Tổng hợp '!I11
A95: Mùa thi | B95: 2026 | C95: 2026 | D95: https://rakhoi.vlu.edu.vn/ | E95: Bảng Sinh viên: 23h59 ngày 20/03/2026; Bảng Học sinh: 23h59 ngày 26/03/2026 | F95: ='Tổng hợp '!J11
A96: Deadline đăng ký | B96: Bảng Sinh viên: 23h59 ngày 20/03/2026; Bảng Học sinh: 23h59 ngày 26/03/2026 | C96: Bảng Sinh viên: 23h59 ngày 20/03/2026; Bảng Học sinh: 23h59 ngày 26/03/2026 | D96: https://rakhoi.vlu.edu.vn/ | E96: Bảng Sinh viên: 23h59 ngày 20/03/2026; Bảng Học sinh: 23h59 ngày 26/03/2026 | F96: ='Tổng hợp '!K11
A97: Trạng thái | B97: Đã kết thúc đăng ký | C97: Đã kết thúc đăng ký | D97: https://rakhoi.vlu.edu.vn/ | E97: Bảng Sinh viên: 23h59 ngày 20/03/2026; Bảng Học sinh: 23h59 ngày 26/03/2026 | F97: ='Tổng hợp '!L11
A98: Link nguồn chính thức | B98: https://rakhoi.vlu.edu.vn/ | C98: https://rakhoi.vlu.edu.vn/ | D98: https://rakhoi.vlu.edu.vn/ | E98: Bảng Sinh viên: 23h59 ngày 20/03/2026; Bảng Học sinh: 23h59 ngày 26/03/2026 | F98: ='Tổng hợp '!M11
A100: 🏆 CUỘC THI: TEC STARTUP PROGRAM 2026 [Liên kết tự động hàng #12 ở trang 'Tổng hợp ']
A101: Tên Cột Trong Excel | B101: Giá Trị Sẽ Ghi Vào File | C101: Nội dung từ web | D101: Link bài viết | E101: Ngày đăng bài (nếu có) | F101: Vị trí liên kết trang Tổng hợp
A102: Tên cuộc thi | B102: TEC Startup Program 2026 | C102: TEC Startup Program 2026 | D102: http://startupprogram.tec-ftu.com/ | E102: 31/08/2026 (cá nhân) – 30/09/2026 (đội thi) lúc 23h59 | F102: ='Tổng hợp '!A12
A103: Lĩnh vực | B103: Khởi nghiệp | C103: Khởi nghiệp (Không giới hạn lĩnh vực đề án) | D103: http://startupprogram.tec-ftu.com/ | E103: 31/08/2026 (cá nhân) – 30/09/2026 (đội thi) lúc 23h59 | F103: ='Tổng hợp '!B12
A104: Đơn vị tổ chức | B104: CLB Nhà Doanh nghiệp Tương lai - Trường Đại học Ngoại thương (TEC FTU) | C104: CLB Nhà Doanh nghiệp Tương lai - Trường Đại học Ngoại thương (TEC FTU) | D104: http://startupprogram.tec-ftu.com/ | E104: 31/08/2026 (cá nhân) – 30/09/2026 (đội thi) lúc 23h59 | F104: ='Tổng hợp '!C12
A105: Mô tả ngắn gọn | B105: Startup Program 2026 là chương trình hoàn toàn miễn phí, đóng vai trò bệ phóng cho các dự án khởi nghiệp giai đoạn đầu dành cho học sinh, sinh viên toàn quốc. Chương trình trang bị kiến thức thực chiến, kết nối mentor và hỗ trợ hiện thực hóa ý tưởng thành mô hình kinh doanh khả thi. | C105: Startup Program 2026 là chương trình hoàn toàn miễn phí, đóng vai trò bệ phóng cho các dự án khởi nghiệp giai đoạn đầu dành cho học sinh, sinh viên toàn quốc. Chương trình trang bị kiến thức thực chiến, kết nối mentor và hỗ trợ hiện thực hóa ý tưởng thành mô hình kinh doanh khả thi. | D105: http://startupprogram.tec-ftu.com/ | E105: 31/08/2026 (cá nhân) – 30/09/2026 (đội thi) lúc 23h59 | F105: ='Tổng hợp '!D12
A106: Đối tượng tham gia | B106: Học sinh, sinh viên, người đi làm từ 17–24 tuổi trên toàn quốc; có hoặc chưa có ý tưởng startup đều được tham gia | C106: Học sinh, sinh viên, người đi làm từ 17–24 tuổi trên toàn quốc; có hoặc chưa có ý tưởng startup đều được tham gia | D106: http://startupprogram.tec-ftu.com/ | E106: 31/08/2026 (cá nhân) – 30/09/2026 (đội thi) lúc 23h59 | F106: ='Tổng hợp '!E12
...

Sheet Startup 
A1: Tên cuộc thi | B1: Lĩnh vực | C1: Đơn vị tổ chức | D1: Mô tả ngắn gọn | E1: Đối tượng tham gia | F1: Hình thức tham gia | G1: Cơ cấu vòng thi | H1: Cơ cấu giải thưởng | I1: Các mốc thời gian | J1: Mùa thi | K1: Deadline đăng ký | L1: Trạng thái | M1: Link nguồn chính thức
A2: Khởi nghiệp cùng Kawai | B2: Khởi nghiệp
A3: Khởi nghiệp kinh doanh | B3: Khởi nghiệp
A4: Khởi nghiệp trẻ | B4: Khởi nghiệp
A5: Khởi nghiệp sinh viên - Biz4Good | B5: Khởi nghiệp
A6: Khởi nghiệp tạo tác động xã hội - I impACT | B6: Khởi nghiệp
A7: Thử thách sáng tạo xã hội Việt Nam | B7: Khởi nghiệp
A8: KMAC - FTU Global Innovative Ideads Contest | B8: Khởi nghiệp
A9: Khởi nghiệp sáng tạo "RnD TO STARTUP" | B9: Khởi nghiệp
A10: Startup Runway | B10: Khởi nghiệp
A11: Ra khơi | B11: Khởi nghiệp
A12: Startup Program | B12: Khởi nghiệp
A13: Ý tưởng kinh doanh | B13: Khởi nghiệp
... A33: Giải thưởng Sáng tạo Tương lai – VietFuture Awards | B33: Khởi nghiệp
